{"code":0,"msg":"Success","data":{"pageIndex":1,"pageCount":1,"list":[{"lightning":"0","hasAnalysis":0,"isCollect":0,"id":"2399279","matchId":"2399279","league":"英格兰超级联赛","leagueShort":"英超","leagueColor":"#FF3333","home":"布伦特福德","away":"曼彻斯特城","HomeTeamID":365,"GuestTeamID":26,"home_img":"https:\/\/images.footballant.com\/team\/365.png!webp","away_img":"https:\/\/images.footballant.com\/team\/26.png!webp","sclassID":"36","league_img":"https:\/\/images.footballant.com\/sclass\/36.png!webp","homeScore":1,"awayScore":3,"homeHalfScore":1,"awayHalfScore":1,"homered":0,"awayRed":0,"homeYellow":1,"awayYellow":0,"homeCorner":8,"guestCorner":13,"homeHalfCorner":4,"guestHalfCorner":12,"match_date":"02-06 04:00","match_time":"2024\/02\/06 04:00:00","match_time_timestamp":1707163200000,"state":"-1","explainList":"2;|;;;;","start_time":"2024\/02\/06 04:00:00","MatchTime2_timestamp":1707167105000,"start_time_timestamp":1707163200000,"event_list":[{"Minute":"3","ClassType":"1","ScheduleType":"4","ScheduleID":"2399279","PlayerName":null,"PlayerID":null,"PlayerID2":"0","PlayerName_J":null},{"Minute":"11","ClassType":"0","ScheduleType":"4","ScheduleID":"2399279","PlayerName":null,"PlayerID":null,"PlayerID2":"0","PlayerName_J":null},{"Minute":"12","ClassType":"0","ScheduleType":"4","ScheduleID":"2399279","PlayerName":null,"PlayerID":null,"PlayerID2":"0","PlayerName_J":null},{"Minute":"14","ClassType":"0","ScheduleType":"4","ScheduleID":"2399279","PlayerName":null,"PlayerID":null,"PlayerID2":"0","PlayerName_J":null},{"Minute":"15","ClassType":"0","ScheduleType":"4","ScheduleID":"2399279","PlayerName":null,"PlayerID":null,"PlayerID2":"0","PlayerName_J":null},{"Minute":"20","ClassType":"0","ScheduleType":"4","ScheduleID":"2399279","PlayerName":null,"PlayerID":null,"PlayerID2":"0","PlayerName_J":null},{"Minute":"21","ClassType":"1","ScheduleType":"1","ScheduleID":"2399279","PlayerName":"Neal Maupay(Assists:Mark Flekken)","PlayerID":"105404","PlayerID2":"0","PlayerName_J":"莫派 (助攻:弗雷肯)"},{"Minute":"23","ClassType":"0","ScheduleType":"4","ScheduleID":"2399279","PlayerName":null,"PlayerID":null,"PlayerID2":"0","PlayerName_J":null},{"Minute":"28","ClassType":"0","ScheduleType":"4","ScheduleID":"2399279","PlayerName":null,"PlayerID":null,"PlayerID2":"0","PlayerName_J":null},{"Minute":"30","ClassType":"0","ScheduleType":"4","ScheduleID":"2399279","PlayerName":null,"PlayerID":null,"PlayerID2":"0","PlayerName_J":null},{"Minute":"31","ClassType":"1","ScheduleType":"3","ScheduleID":"2399279","PlayerName":"Neal Maupay","PlayerID":"105404","PlayerID2":"0","PlayerName_J":"莫派"},{"Minute":"33","ClassType":"0","ScheduleType":"4","ScheduleID":"2399279","PlayerName":null,"PlayerID":null,"PlayerID2":"0","PlayerName_J":null},{"Minute":"38","ClassType":"1","ScheduleType":"4","ScheduleID":"2399279","PlayerName":null,"PlayerID":null,"PlayerID2":"0","PlayerName_J":null},{"Minute":"38","ClassType":"1","ScheduleType":"4","ScheduleID":"2399279","PlayerName":null,"PlayerID":null,"PlayerID2":"0","PlayerName_J":null},{"Minute":"39","ClassType":"1","ScheduleType":"4","ScheduleID":"2399279","PlayerName":null,"PlayerID":null,"PlayerID2":"0","PlayerName_J":null},{"Minute":"44","ClassType":"0","ScheduleType":"4","ScheduleID":"2399279","PlayerName":null,"PlayerID":null,"PlayerID2":"0","PlayerName_J":null},{"Minute":"45","ClassType":"0","ScheduleType":"1","ScheduleID":"2399279","PlayerName":"Phil Foden","PlayerID":"150245","PlayerID2":"0","PlayerName_J":"福登"},{"Minute":"45","ClassType":"0","ScheduleType":"4","ScheduleID":"2399279","PlayerName":null,"PlayerID":null,"PlayerID2":"0","PlayerName_J":null},{"Minute":"45","ClassType":"0","ScheduleType":"4","ScheduleID":"2399279","PlayerName":null,"PlayerID":null,"PlayerID2":"0","PlayerName_J":null},{"Minute":"53","ClassType":"0","ScheduleType":"1","ScheduleID":"2399279","PlayerName":"Phil Foden(Assists:Kevin De Bruyne)","PlayerID":"150245","PlayerID2":"0","PlayerName_J":"福登 (助攻:德布劳内)"},{"Minute":"59","ClassType":"0","ScheduleType":"4","ScheduleID":"2399279","PlayerName":null,"PlayerID":null,"PlayerID2":"0","PlayerName_J":null},{"Minute":"61","ClassType":"1","ScheduleType":"4","ScheduleID":"2399279","PlayerName":null,"PlayerID":null,"PlayerID2":"0","PlayerName_J":null},{"Minute":"63","ClassType":"1","ScheduleType":"4","ScheduleID":"2399279","PlayerName":null,"PlayerID":null,"PlayerID2":"0","PlayerName_J":null},{"Minute":"70","ClassType":"0","ScheduleType":"1","ScheduleID":"2399279","PlayerName":"Phil Foden(Assists:Erling Haaland)","PlayerID":"150245","PlayerID2":"0","PlayerName_J":"福登 (助攻:哈兰德)"},{"Minute":"71","ClassType":"0","ScheduleType":"11","ScheduleID":"2399279","PlayerName":"Jeremy Doku↑Bernardo Mota Veiga de Carvalho e Silva↓","PlayerID":"172257","PlayerID2":"0","PlayerName_J":"多库↑B.席尔瓦↓"},{"Minute":"76","ClassType":"1","ScheduleType":"11","ScheduleID":"2399279","PlayerName":"Yegor Yarmolyuk↑Vitaly Janelt↓","PlayerID":"215569","PlayerID2":"0","PlayerName_J":"叶戈尔·亚尔莫柳克↑庄拿达↓"},{"Minute":"76","ClassType":"1","ScheduleType":"11","ScheduleID":"2399279","PlayerName":"Keane Lewis-Potter↑Mads Roerslev Rasmussen↓","PlayerID":"177069","PlayerID2":"0","PlayerName_J":"波特↑基辛拉斯姆森↓"},{"Minute":"77","ClassType":"1","ScheduleType":"11","ScheduleID":"2399279","PlayerName":"Mikkel Damsgaard↑Mathias Jensen↓","PlayerID":"163242","PlayerID2":"0","PlayerName_J":"达姆斯加德↑延森↓"},{"Minute":"78","ClassType":"1","ScheduleType":"4","ScheduleID":"2399279","PlayerName":null,"PlayerID":null,"PlayerID2":"0","PlayerName_J":null},{"Minute":"79","ClassType":"1","ScheduleType":"11","ScheduleID":"2399279","PlayerName":"Kristoffer Ajer↑Sergio Reguilón↓","PlayerID":"125876","PlayerID2":"0","PlayerName_J":"K.阿耶↑雷吉隆↓"},{"Minute":"86","ClassType":"0","ScheduleType":"11","ScheduleID":"2399279","PlayerName":"Mateo Kovacic↑Erling Haaland↓","PlayerID":"79276","PlayerID2":"0","PlayerName_J":"科瓦契奇↑哈兰德↓"},{"Minute":"90","ClassType":"1","ScheduleType":"11","ScheduleID":"2399279","PlayerName":"Shandon Baptiste↑Neal Maupay↓","PlayerID":"164108","PlayerID2":"0","PlayerName_J":"巴蒂斯特↑莫派↓"},{"Minute":"90","ClassType":"1","ScheduleType":"4","ScheduleID":"2399279","PlayerName":null,"PlayerID":null,"PlayerID2":"0","PlayerName_J":null}],"scheduleEventList":{"event_info":[],"technic":{"14":{"leixing":"14","home_info":"28%","away_info":"72%"},"46":{"leixing":"46","home_info":"28%","away_info":"72%"},"20":{"leixing":"20","home_info":"12","away_info":"5"},"0":{"leixing":"0","home_info":"","away_info":"*"},"43":{"leixing":"43","home_info":"58","away_info":"139"},"41":{"leixing":"41","home_info":"267","away_info":"719"},"42":{"leixing":"42","home_info":"73%","away_info":"90%"},"15":{"leixing":"15","home_info":"25","away_info":"23"},"36":{"leixing":"36","home_info":"13","away_info":"11"},"40":{"leixing":"40","home_info":"10","away_info":"20"},"44":{"leixing":"44","home_info":"26","away_info":"98"},"45":{"leixing":"45","home_info":"4","away_info":"12"},"6":{"leixing":"6","home_info":"8","away_info":"13"},"3":{"leixing":"3","home_info":"9","away_info":"25"},"34":{"leixing":"34","home_info":"6","away_info":"10"},"19":{"leixing":"19","home_info":"17","away_info":"11"},"37":{"leixing":"37","home_info":"3","away_info":"7"},"38":{"leixing":"38","home_info":"17","away_info":"11"},"39":{"leixing":"39","home_info":"2","away_info":"9"},"4":{"leixing":"4","home_info":"3","away_info":"15"},"16":{"leixing":"16","home_info":"12","away_info":"2"},"8":{"leixing":"8","home_info":"4","away_info":"4"},"9":{"leixing":"9","home_info":"2","away_info":"0"},"23":{"leixing":"23","home_info":"1","away_info":"2"},"11":{"leixing":"11","home_info":"1","away_info":"0"},"5":{"leixing":"5","home_info":"2","away_info":"4"}},"technicList":[{"leixing":"14","home_info":"28%","away_info":"72%"},{"leixing":"46","home_info":"28%","away_info":"72%"},{"leixing":"20","home_info":"12","away_info":"5"},{"leixing":"0","home_info":"","away_info":"*"},{"leixing":"43","home_info":"58","away_info":"139"},{"leixing":"41","home_info":"267","away_info":"719"},{"leixing":"42","home_info":"73%","away_info":"90%"},{"leixing":"15","home_info":"25","away_info":"23"},{"leixing":"36","home_info":"13","away_info":"11"},{"leixing":"40","home_info":"10","away_info":"20"},{"leixing":"44","home_info":"26","away_info":"98"},{"leixing":"45","home_info":"4","away_info":"12"},{"leixing":"6","home_info":"8","away_info":"13"},{"leixing":"3","home_info":"9","away_info":"25"},{"leixing":"34","home_info":"6","away_info":"10"},{"leixing":"19","home_info":"17","away_info":"11"},{"leixing":"37","home_info":"3","away_info":"7"},{"leixing":"38","home_info":"17","away_info":"11"},{"leixing":"39","home_info":"2","away_info":"9"},{"leixing":"4","home_info":"3","away_info":"15"},{"leixing":"16","home_info":"12","away_info":"2"},{"leixing":"8","home_info":"4","away_info":"4"},{"leixing":"9","home_info":"2","away_info":"0"},{"leixing":"23","home_info":"1","away_info":"2"},{"leixing":"11","home_info":"1","away_info":"0"},{"leixing":"5","home_info":"2","away_info":"4"}]},"o_odds":{"o_home_first":"8","o_stand_first":"4.2","o_guest_first":"1.45","o_home":"7.5","o_stand":"5.25","o_guest":"1.4","o_home_r":"451","o_stand_r":"51","o_guest_r":"1","modifyTime":"2024-02-06 05:48:41","closePan":""},"y_odds":{"y_first_goal":"1.25","y_first_upOdds":"","y_first_downOdds":"","y_goal":"0.00","y_up":"1.40","y_down":"0.62","y_goal_r":"1.25","y_up_r":"1.04","y_down_r":"0.86","modifyTime":"2024-02-06 05:52:57","closePan":""},"total_score_odds":{"first_total_score_goal":"3","first_total_score_upOdds":"1.07","first_total_score_downOdds":"0.83","total_score_goal":"4.5","total_score_up":"7.1","total_score_down":"0.09","total_score_goal_r":"3","total_score_upOdds_r":"0.85","total_score_downOdds_r":"1.05","modifyTime":"2024-02-06 05:52:57","closePan":""}},{"lightning":"0","hasAnalysis":0,"isCollect":0,"id":"2399277","matchId":"2399277","league":"英格兰超级联赛","leagueShort":"英超","leagueColor":"#FF3333","home":"阿森纳","away":"利物浦","HomeTeamID":19,"GuestTeamID":25,"home_img":"https:\/\/images.footballant.com\/team\/19.png!webp","away_img":"https:\/\/images.footballant.com\/team\/25.png!webp","sclassID":"36","league_img":"https:\/\/images.footballant.com\/sclass\/36.png!webp","homeScore":3,"awayScore":1,"homeHalfScore":1,"awayHalfScore":1,"homered":0,"awayRed":1,"homeYellow":6,"awayYellow":4,"homeCorner":2,"guestCorner":4,"homeHalfCorner":0,"guestHalfCorner":1,"match_date":"02-05 00:30","match_time":"2024\/02\/05 00:30:00","match_time_timestamp":1707064200000,"state":"-1","explainList":"2;|;;;;","start_time":"2024\/02\/05 00:30:00","MatchTime2_timestamp":1707068100000,"start_time_timestamp":1707064200000,"event_list":[{"Minute":"14","ClassType":"1","ScheduleType":"1","ScheduleID":"2399277","PlayerName":"Bukayo Saka","PlayerID":"171322","PlayerID2":"0","PlayerName_J":"萨卡"},{"Minute":"25","ClassType":"0","ScheduleType":"3","ScheduleID":"2399277","PlayerName":"Joseph Gomez","PlayerID":"124365","PlayerID2":"0","PlayerName_J":"戈麦斯"},{"Minute":"29","ClassType":"0","ScheduleType":"4","ScheduleID":"2399277","PlayerName":null,"PlayerID":null,"PlayerID2":"0","PlayerName_J":null},{"Minute":"31","ClassType":"1","ScheduleType":"3","ScheduleID":"2399277","PlayerName":"Benjamin William White","PlayerID":"145438","PlayerID2":"0","PlayerName_J":"怀特"},{"Minute":"45","ClassType":"0","ScheduleType":"8","ScheduleID":"2399277","PlayerName":"Gabriel Dos Santos Magalhaes","PlayerID":"151417","PlayerID2":"0","PlayerName_J":"加布里埃尔"},{"Minute":"46","ClassType":"1","ScheduleType":"11","ScheduleID":"2399277","PlayerName":"Jakub Kiwior↑Olexandr Zinchenko↓","PlayerID":"174939","PlayerID2":"0","PlayerName_J":"基维奥尔↑津琴科↓"},{"Minute":"53","ClassType":"1","ScheduleType":"4","ScheduleID":"2399277","PlayerName":null,"PlayerID":null,"PlayerID2":"0","PlayerName_J":null},{"Minute":"55","ClassType":"0","ScheduleType":"3","ScheduleID":"2399277","PlayerName":"Ibrahima Konate","PlayerID":"150617","PlayerID2":"0","PlayerName_J":"科纳特"},{"Minute":"57","ClassType":"1","ScheduleType":"3","ScheduleID":"2399277","PlayerName":"Gabriel Dos Santos Magalhaes","PlayerID":"151417","PlayerID2":"0","PlayerName_J":"加布里埃尔"},{"Minute":"58","ClassType":"0","ScheduleType":"11","ScheduleID":"2399277","PlayerName":"Andrew Robertson↑Trent Arnold↓","PlayerID":"106066","PlayerID2":"0","PlayerName_J":"罗伯逊↑阿诺德↓"},{"Minute":"58","ClassType":"0","ScheduleType":"11","ScheduleID":"2399277","PlayerName":"Darwin Gabriel Nunez Ribeiro↑Cody Gakpo↓","PlayerID":"174011","PlayerID2":"0","PlayerName_J":"努涅斯↑加克波↓"},{"Minute":"58","ClassType":"0","ScheduleType":"11","ScheduleID":"2399277","PlayerName":"Harvey Elliott↑Ryan Jiro Gravenberch↓","PlayerID":"175078","PlayerID2":"0","PlayerName_J":"埃利奥特↑赫拉芬贝赫↓"},{"Minute":"59","ClassType":"0","ScheduleType":"4","ScheduleID":"2399277","PlayerName":null,"PlayerID":null,"PlayerID2":"0","PlayerName_J":null},{"Minute":"61","ClassType":"1","ScheduleType":"4","ScheduleID":"2399277","PlayerName":null,"PlayerID":null,"PlayerID2":"0","PlayerName_J":null},{"Minute":"67","ClassType":"1","ScheduleType":"1","ScheduleID":"2399277","PlayerName":"Gabriel Teodoro Martinelli Silva","PlayerID":"168935","PlayerID2":"0","PlayerName_J":"马丁内利"},{"Minute":"69","ClassType":"1","ScheduleType":"3","ScheduleID":"2399277","PlayerName":"Jakub Kiwior","PlayerID":"174939","PlayerID2":"0","PlayerName_J":"基维奥尔"},{"Minute":"74","ClassType":"1","ScheduleType":"11","ScheduleID":"2399277","PlayerName":"Leandro Trossard↑Gabriel Teodoro Martinelli Silva↓","PlayerID":"102096","PlayerID2":"0","PlayerName_J":"特罗萨德↑马丁内利↓"},{"Minute":"77","ClassType":"0","ScheduleType":"4","ScheduleID":"2399277","PlayerName":null,"PlayerID":null,"PlayerID2":"0","PlayerName_J":null},{"Minute":"79","ClassType":"1","ScheduleType":"11","ScheduleID":"2399277","PlayerName":"Reiss Nelson↑Bukayo Saka↓","PlayerID":"155054","PlayerID2":"0","PlayerName_J":"尼尔森↑萨卡↓"},{"Minute":"83","ClassType":"0","ScheduleType":"4","ScheduleID":"2399277","PlayerName":null,"PlayerID":null,"PlayerID2":"0","PlayerName_J":null},{"Minute":"85","ClassType":"0","ScheduleType":"11","ScheduleID":"2399277","PlayerName":"Thiago Alcantara do Nascimento↑Joseph Gomez↓","PlayerID":"70104","PlayerID2":"0","PlayerName_J":"蒂亚戈↑戈麦斯↓"},{"Minute":"88","ClassType":"0","ScheduleType":"9","ScheduleID":"2399277","PlayerName":"Ibrahima Konate","PlayerID":"150617","PlayerID2":"0","PlayerName_J":"科纳特"},{"Minute":"90","ClassType":"0","ScheduleType":"3","ScheduleID":"2399277","PlayerName":"Darwin Gabriel Nunez Ribeiro","PlayerID":"174011","PlayerID2":"0","PlayerName_J":"努涅斯"},{"Minute":"90","ClassType":"1","ScheduleType":"3","ScheduleID":"2399277","PlayerName":"William Saliba","PlayerID":"167450","PlayerID2":"0","PlayerName_J":"萨利巴"},{"Minute":"90","ClassType":"1","ScheduleType":"1","ScheduleID":"2399277","PlayerName":"Leandro Trossard(Assists:Jakub Kiwior)","PlayerID":"102096","PlayerID2":"0","PlayerName_J":"特罗萨德 (助攻:基维奥尔)"},{"Minute":"90","ClassType":"1","ScheduleType":"3","ScheduleID":"2399277","PlayerName":"Declan Rice","PlayerID":"150472","PlayerID2":"0","PlayerName_J":"赖斯"},{"Minute":"90","ClassType":"1","ScheduleType":"3","ScheduleID":"2399277","PlayerName":"Kai Havertz","PlayerID":"147555","PlayerID2":"0","PlayerName_J":"哈弗茨"}],"scheduleEventList":{"event_info":[],"technic":{"14":{"leixing":"14","home_info":"43%","away_info":"57%"},"46":{"leixing":"46","home_info":"46%","away_info":"54%"},"43":{"leixing":"43","home_info":"93","away_info":"92"},"41":{"leixing":"41","home_info":"369","away_info":"494"},"36":{"leixing":"36","home_info":"16","away_info":"21"},"42":{"leixing":"42","home_info":"80%","away_info":"84%"},"15":{"leixing":"15","home_info":"40","away_info":"34"},"40":{"leixing":"40","home_info":"19","away_info":"28"},"44":{"leixing":"44","home_info":"57","away_info":"34"},"8":{"leixing":"8","home_info":"12","away_info":"13"},"0":{"leixing":"0","home_info":"","away_info":"*"},"20":{"leixing":"20","home_info":"12","away_info":"8"},"5":{"leixing":"5","home_info":"10","away_info":"11"},"9":{"leixing":"9","home_info":"3","away_info":"1"},"38":{"leixing":"38","home_info":"19","away_info":"11"},"39":{"leixing":"39","home_info":"7","away_info":"7"},"19":{"leixing":"19","home_info":"19","away_info":"11"},"3":{"leixing":"3","home_info":"15","away_info":"10"},"34":{"leixing":"34","home_info":"8","away_info":"9"},"16":{"leixing":"16","home_info":"1","away_info":"4"},"4":{"leixing":"4","home_info":"7","away_info":"1"},"37":{"leixing":"37","home_info":"5","away_info":"2"},"11":{"leixing":"11","home_info":"6","away_info":"3"},"45":{"leixing":"45","home_info":"0","away_info":"1"},"6":{"leixing":"6","home_info":"2","away_info":"4"},"13":{"leixing":"13","home_info":"0","away_info":"1"},"23":{"leixing":"23","home_info":"1","away_info":"0"}},"technicList":[{"leixing":"14","home_info":"43%","away_info":"57%"},{"leixing":"46","home_info":"46%","away_info":"54%"},{"leixing":"43","home_info":"93","away_info":"92"},{"leixing":"41","home_info":"369","away_info":"494"},{"leixing":"36","home_info":"16","away_info":"21"},{"leixing":"42","home_info":"80%","away_info":"84%"},{"leixing":"15","home_info":"40","away_info":"34"},{"leixing":"40","home_info":"19","away_info":"28"},{"leixing":"44","home_info":"57","away_info":"34"},{"leixing":"8","home_info":"12","away_info":"13"},{"leixing":"0","home_info":"","away_info":"*"},{"leixing":"20","home_info":"12","away_info":"8"},{"leixing":"5","home_info":"10","away_info":"11"},{"leixing":"9","home_info":"3","away_info":"1"},{"leixing":"38","home_info":"19","away_info":"11"},{"leixing":"39","home_info":"7","away_info":"7"},{"leixing":"19","home_info":"19","away_info":"11"},{"leixing":"3","home_info":"15","away_info":"10"},{"leixing":"34","home_info":"8","away_info":"9"},{"leixing":"16","home_info":"1","away_info":"4"},{"leixing":"4","home_info":"7","away_info":"1"},{"leixing":"37","home_info":"5","away_info":"2"},{"leixing":"11","home_info":"6","away_info":"3"},{"leixing":"45","home_info":"0","away_info":"1"},{"leixing":"6","home_info":"2","away_info":"4"},{"leixing":"13","home_info":"0","away_info":"1"},{"leixing":"23","home_info":"1","away_info":"0"}]},"o_odds":{"o_home_first":"2","o_stand_first":"3.8","o_guest_first":"3.5","o_home":"2.1","o_stand":"3.6","o_guest":"3.25","o_home_r":"1.04","o_stand_r":"13","o_guest_r":"201","modifyTime":"2024-02-05 02:21:10","closePan":""},"y_odds":{"y_first_goal":"-0.50","y_first_upOdds":"","y_first_downOdds":"","y_goal":"0.00","y_up":"0.50","y_down":"1.70","y_goal_r":"-0.25","y_up_r":"0.91","y_down_r":"0.99","modifyTime":"2024-02-05 02:25:13","closePan":""},"total_score_odds":{"first_total_score_goal":"3","first_total_score_upOdds":"1.03","first_total_score_downOdds":"0.87","total_score_goal":"4.5","total_score_up":"7.5","total_score_down":"0.08","total_score_goal_r":"2.75","total_score_upOdds_r":"0.88","total_score_downOdds_r":"1.02","modifyTime":"2024-02-05 02:25:13","closePan":""}},{"lightning":"0","hasAnalysis":0,"isCollect":0,"id":"2399278","matchId":"2399278","league":"英格兰超级联赛","leagueShort":"英超","leagueColor":"#FF3333","home":"伯恩茅斯","away":"诺丁汉森林","HomeTeamID":348,"GuestTeamID":49,"home_img":"https:\/\/images.footballant.com\/team\/348.png!webp","away_img":"https:\/\/images.footballant.com\/team\/49.png!webp","sclassID":"36","league_img":"https:\/\/images.footballant.com\/sclass\/36.png!webp","homeScore":1,"awayScore":1,"homeHalfScore":1,"awayHalfScore":1,"homered":1,"awayRed":0,"homeYellow":3,"awayYellow":2,"homeCorner":11,"guestCorner":6,"homeHalfCorner":6,"guestHalfCorner":4,"match_date":"02-04 22:00","match_time":"2024\/02\/04 22:00:00","match_time_timestamp":1707055200000,"state":"-1","explainList":"1;|;;;;","start_time":"2024\/02\/04 22:00:00","MatchTime2_timestamp":1707059391000,"start_time_timestamp":1707055200000,"event_list":[{"Minute":"2","ClassType":"1","ScheduleType":"4","ScheduleID":"2399278","PlayerName":null,"PlayerID":null,"PlayerID2":"0","PlayerName_J":null},{"Minute":"5","ClassType":"1","ScheduleType":"4","ScheduleID":"2399278","PlayerName":null,"PlayerID":null,"PlayerID2":"0","PlayerName_J":null},{"Minute":"5","ClassType":"1","ScheduleType":"1","ScheduleID":"2399278","PlayerName":"Justin Kluivert(Assists:Luis Sinisterra)","PlayerID":"150184","PlayerID2":"0","PlayerName_J":"克鲁伊维特 (助攻:西尼斯特拉)"},{"Minute":"12","ClassType":"1","ScheduleType":"4","ScheduleID":"2399278","PlayerName":null,"PlayerID":null,"PlayerID2":"0","PlayerName_J":null},{"Minute":"17","ClassType":"1","ScheduleType":"4","ScheduleID":"2399278","PlayerName":null,"PlayerID":null,"PlayerID2":"0","PlayerName_J":null},{"Minute":"21","ClassType":"1","ScheduleType":"4","ScheduleID":"2399278","PlayerName":null,"PlayerID":null,"PlayerID2":"0","PlayerName_J":null},{"Minute":"23","ClassType":"1","ScheduleType":"3","ScheduleID":"2399278","PlayerName":"Marcos Senesi","PlayerID":"148207","PlayerID2":"0","PlayerName_J":"塞内西"},{"Minute":"28","ClassType":"0","ScheduleType":"4","ScheduleID":"2399278","PlayerName":null,"PlayerID":null,"PlayerID2":"0","PlayerName_J":null},{"Minute":"29","ClassType":"0","ScheduleType":"4","ScheduleID":"2399278","PlayerName":null,"PlayerID":null,"PlayerID2":"0","PlayerName_J":null},{"Minute":"31","ClassType":"1","ScheduleType":"4","ScheduleID":"2399278","PlayerName":null,"PlayerID":null,"PlayerID2":"0","PlayerName_J":null},{"Minute":"35","ClassType":"1","ScheduleType":"3","ScheduleID":"2399278","PlayerName":"Justin Kluivert","PlayerID":"150184","PlayerID2":"0","PlayerName_J":"克鲁伊维特"},{"Minute":"38","ClassType":"0","ScheduleType":"4","ScheduleID":"2399278","PlayerName":null,"PlayerID":null,"PlayerID2":"0","PlayerName_J":null},{"Minute":"45","ClassType":"0","ScheduleType":"1","ScheduleID":"2399278","PlayerName":"Callum Hudson-Odoi","PlayerID":"161723","PlayerID2":"0","PlayerName_J":"奥多伊"},{"Minute":"45","ClassType":"0","ScheduleType":"4","ScheduleID":"2399278","PlayerName":null,"PlayerID":null,"PlayerID2":"0","PlayerName_J":null},{"Minute":"46","ClassType":"1","ScheduleType":"11","ScheduleID":"2399278","PlayerName":"Marcus Tavernier↑Antoine Semenyo↓","PlayerID":"159869","PlayerID2":"0","PlayerName_J":"塔维尼尔↑希门尼约↓"},{"Minute":"47","ClassType":"0","ScheduleType":"4","ScheduleID":"2399278","PlayerName":null,"PlayerID":null,"PlayerID2":"0","PlayerName_J":null},{"Minute":"52","ClassType":"1","ScheduleType":"4","ScheduleID":"2399278","PlayerName":null,"PlayerID":null,"PlayerID2":"0","PlayerName_J":null},{"Minute":"55","ClassType":"0","ScheduleType":"3","ScheduleID":"2399278","PlayerName":"Andrew Omobamidele","PlayerID":"201676","PlayerID2":"0","PlayerName_J":"A.奥莫巴米德尔"},{"Minute":"56","ClassType":"1","ScheduleType":"11","ScheduleID":"2399278","PlayerName":"Alex Scott↑Ryan Christie↓","PlayerID":"105881","PlayerID2":"0","PlayerName_J":"斯科特↑克里斯蒂↓"},{"Minute":"56","ClassType":"1","ScheduleType":"11","ScheduleID":"2399278","PlayerName":"Phillip Billing↑Justin Kluivert↓","PlayerID":"120672","PlayerID2":"0","PlayerName_J":"比林↑克鲁伊维特↓"},{"Minute":"65","ClassType":"0","ScheduleType":"4","ScheduleID":"2399278","PlayerName":null,"PlayerID":null,"PlayerID2":"0","PlayerName_J":null},{"Minute":"71","ClassType":"1","ScheduleType":"11","ScheduleID":"2399278","PlayerName":"Dango Ouattara↑Luis Sinisterra↓","PlayerID":"213867","PlayerID2":"0","PlayerName_J":"瓦塔拉↑西尼斯特拉↓"},{"Minute":"72","ClassType":"0","ScheduleType":"11","ScheduleID":"2399278","PlayerName":"Danilo Dos Santos De Oliveira↑Nicolas Dominguez↓","PlayerID":"200168","PlayerID2":"0","PlayerName_J":"D.奥利维拉↑多明古耶斯↓"},{"Minute":"73","ClassType":"1","ScheduleType":"4","ScheduleID":"2399278","PlayerName":null,"PlayerID":null,"PlayerID2":"0","PlayerName_J":null},{"Minute":"73","ClassType":"0","ScheduleType":"3","ScheduleID":"2399278","PlayerName":"Ryan Yates","PlayerID":"149642","PlayerID2":"0","PlayerName_J":"耶茨"},{"Minute":"74","ClassType":"1","ScheduleType":"4","ScheduleID":"2399278","PlayerName":null,"PlayerID":null,"PlayerID2":"0","PlayerName_J":null},{"Minute":"78","ClassType":"0","ScheduleType":"11","ScheduleID":"2399278","PlayerName":"Giovanni Reyna↑Anthony Elanga↓","PlayerID":"177398","PlayerID2":"0","PlayerName_J":"雷纳↑A.伊兰加↓"},{"Minute":"78","ClassType":"0","ScheduleType":"11","ScheduleID":"2399278","PlayerName":"Gonzalo Montiel↑Neco Williams↓","PlayerID":"147655","PlayerID2":"0","PlayerName_J":"蒙蒂埃尔↑威廉姆斯↓"},{"Minute":"82","ClassType":"1","ScheduleType":"4","ScheduleID":"2399278","PlayerName":null,"PlayerID":null,"PlayerID2":"0","PlayerName_J":null},{"Minute":"83","ClassType":"1","ScheduleType":"11","ScheduleID":"2399278","PlayerName":"Milos Kerkez↑Lloyd Kelly↓","PlayerID":"222311","PlayerID2":"0","PlayerName_J":"M.科克斯↑凯利↓"},{"Minute":"84","ClassType":"1","ScheduleType":"2","ScheduleID":"2399278","PlayerName":"Phillip Billing","PlayerID":"120672","PlayerID2":"0","PlayerName_J":"比林"},{"Minute":"85","ClassType":"1","ScheduleType":"3","ScheduleID":"2399278","PlayerName":"Norberto Murara Neto","PlayerID":"164464","PlayerID2":"0","PlayerName_J":"内托"},{"Minute":"90","ClassType":"0","ScheduleType":"11","ScheduleID":"2399278","PlayerName":"Rodrigo Duarte Ribeiro↑Callum Hudson-Odoi↓","PlayerID":"225019","PlayerID2":"0","PlayerName_J":"里贝罗↑奥多伊↓"},{"Minute":"90","ClassType":"1","ScheduleType":"4","ScheduleID":"2399278","PlayerName":null,"PlayerID":null,"PlayerID2":"0","PlayerName_J":null}],"scheduleEventList":{"event_info":[],"technic":{"14":{"leixing":"14","home_info":"45%","away_info":"55%"},"46":{"leixing":"46","home_info":"44%","away_info":"56%"},"43":{"leixing":"43","home_info":"111","away_info":"78"},"44":{"leixing":"44","home_info":"65","away_info":"44"},"45":{"leixing":"45","home_info":"6","away_info":"4"},"37":{"leixing":"37","home_info":"7","away_info":"0"},"41":{"leixing":"41","home_info":"321","away_info":"412"},"38":{"leixing":"38","home_info":"15","away_info":"31"},"20":{"leixing":"20","home_info":"12","away_info":"6"},"6":{"leixing":"6","home_info":"11","away_info":"6"},"3":{"leixing":"3","home_info":"9","away_info":"8"},"34":{"leixing":"34","home_info":"7","away_info":"2"},"42":{"leixing":"42","home_info":"69%","away_info":"77%"},"40":{"leixing":"40","home_info":"28","away_info":"16"},"0":{"leixing":"0","home_info":"*","away_info":""},"19":{"leixing":"19","home_info":"15","away_info":"29"},"4":{"leixing":"4","home_info":"2","away_info":"6"},"5":{"leixing":"5","home_info":"19","away_info":"12"},"16":{"leixing":"16","home_info":"4","away_info":"1"},"39":{"leixing":"39","home_info":"9","away_info":"5"},"15":{"leixing":"15","home_info":"37","away_info":"37"},"36":{"leixing":"36","home_info":"15","away_info":"22"},"8":{"leixing":"8","home_info":"12","away_info":"17"},"11":{"leixing":"11","home_info":"3","away_info":"2"},"23":{"leixing":"23","home_info":"1","away_info":"0"},"9":{"leixing":"9","home_info":"1","away_info":"1"},"13":{"leixing":"13","home_info":"1","away_info":"0"}},"technicList":[{"leixing":"14","home_info":"45%","away_info":"55%"},{"leixing":"46","home_info":"44%","away_info":"56%"},{"leixing":"43","home_info":"111","away_info":"78"},{"leixing":"44","home_info":"65","away_info":"44"},{"leixing":"45","home_info":"6","away_info":"4"},{"leixing":"37","home_info":"7","away_info":"0"},{"leixing":"41","home_info":"321","away_info":"412"},{"leixing":"38","home_info":"15","away_info":"31"},{"leixing":"20","home_info":"12","away_info":"6"},{"leixing":"6","home_info":"11","away_info":"6"},{"leixing":"3","home_info":"9","away_info":"8"},{"leixing":"34","home_info":"7","away_info":"2"},{"leixing":"42","home_info":"69%","away_info":"77%"},{"leixing":"40","home_info":"28","away_info":"16"},{"leixing":"0","home_info":"*","away_info":""},{"leixing":"19","home_info":"15","away_info":"29"},{"leixing":"4","home_info":"2","away_info":"6"},{"leixing":"5","home_info":"19","away_info":"12"},{"leixing":"16","home_info":"4","away_info":"1"},{"leixing":"39","home_info":"9","away_info":"5"},{"leixing":"15","home_info":"37","away_info":"37"},{"leixing":"36","home_info":"15","away_info":"22"},{"leixing":"8","home_info":"12","away_info":"17"},{"leixing":"11","home_info":"3","away_info":"2"},{"leixing":"23","home_info":"1","away_info":"0"},{"leixing":"9","home_info":"1","away_info":"1"},{"leixing":"13","home_info":"1","away_info":"0"}]},"o_odds":{"o_home_first":"1.73","o_stand_first":"4","o_guest_first":"4.5","o_home":"1.65","o_stand":"4.33","o_guest":"4.75","o_home_r":"26","o_stand_r":"1.02","o_guest_r":"21","modifyTime":"2024-02-05 00:00:35","closePan":""},"y_odds":{"y_first_goal":"-0.75","y_first_upOdds":"","y_first_downOdds":"","y_goal":"0.00","y_up":"1.50","y_down":"0.57","y_goal_r":"-0.75","y_up_r":"0.82","y_down_r":"1.08","modifyTime":"2024-02-04 23:58:48","closePan":""},"total_score_odds":{"first_total_score_goal":"2.75","first_total_score_upOdds":"0.92","first_total_score_downOdds":"0.98","total_score_goal":"2.5","total_score_up":"7.1","total_score_down":"0.09","total_score_goal_r":"3","total_score_upOdds_r":"0.97","total_score_downOdds_r":"0.93","modifyTime":"2024-02-04 23:58:48","closePan":""}},{"lightning":"0","hasAnalysis":0,"isCollect":0,"id":"2399282","matchId":"2399282","league":"英格兰超级联赛","leagueShort":"英超","leagueColor":"#FF3333","home":"切尔西","away":"狼队","HomeTeamID":24,"GuestTeamID":52,"home_img":"https:\/\/images.footballant.com\/team\/24.png!webp","away_img":"https:\/\/images.footballant.com\/team\/52.png!webp","sclassID":"36","league_img":"https:\/\/images.footballant.com\/sclass\/36.png!webp","homeScore":2,"awayScore":4,"homeHalfScore":1,"awayHalfScore":2,"homered":0,"awayRed":0,"homeYellow":3,"awayYellow":2,"homeCorner":10,"guestCorner":1,"homeHalfCorner":3,"guestHalfCorner":0,"match_date":"02-04 22:00","match_time":"2024\/02\/04 22:00:00","match_time_timestamp":1707055200000,"state":"-1","explainList":"2;|;;;;","start_time":"2024\/02\/04 22:00:00","MatchTime2_timestamp":1707059247000,"start_time_timestamp":1707055200000,"event_list":[{"Minute":"4","ClassType":"1","ScheduleType":"4","ScheduleID":"2399282","PlayerName":null,"PlayerID":null,"PlayerID2":"0","PlayerName_J":null},{"Minute":"9","ClassType":"1","ScheduleType":"4","ScheduleID":"2399282","PlayerName":null,"PlayerID":null,"PlayerID2":"0","PlayerName_J":null},{"Minute":"19","ClassType":"1","ScheduleType":"1","ScheduleID":"2399282","PlayerName":"Cole Jermaine Palmer(Assists:Moises Caicedo)","PlayerID":"191693","PlayerID2":"0","PlayerName_J":"C.帕尔默 (助攻:凯塞多)"},{"Minute":"22","ClassType":"0","ScheduleType":"1","ScheduleID":"2399282","PlayerName":"Matheus Cunha(Assists:Joao Victor Gomes da Silva)","PlayerID":"155454","PlayerID2":"0","PlayerName_J":"库尼亚 (助攻:J.戈麦斯)"},{"Minute":"31","ClassType":"1","ScheduleType":"3","ScheduleID":"2399282","PlayerName":"Malo Gusto","PlayerID":"201037","PlayerID2":"0","PlayerName_J":"古斯托"},{"Minute":"39","ClassType":"0","ScheduleType":"3","ScheduleID":"2399282","PlayerName":"Nelson Cabral Semedo","PlayerID":"105752","PlayerID2":"0","PlayerName_J":"塞梅多"},{"Minute":"40","ClassType":"1","ScheduleType":"4","ScheduleID":"2399282","PlayerName":null,"PlayerID":null,"PlayerID2":"0","PlayerName_J":null},{"Minute":"41","ClassType":"0","ScheduleType":"3","ScheduleID":"2399282","PlayerName":"Pedro Neto","PlayerID":"153294","PlayerID2":"0","PlayerName_J":"内托"},{"Minute":"43","ClassType":"0","ScheduleType":"8","ScheduleID":"2399282","PlayerName":"Axel Disasi","PlayerID":"139615","PlayerID2":"0","PlayerName_J":"迪萨西"},{"Minute":"51","ClassType":"1","ScheduleType":"4","ScheduleID":"2399282","PlayerName":null,"PlayerID":null,"PlayerID2":"0","PlayerName_J":null},{"Minute":"52","ClassType":"1","ScheduleType":"4","ScheduleID":"2399282","PlayerName":null,"PlayerID":null,"PlayerID2":"0","PlayerName_J":null},{"Minute":"56","ClassType":"1","ScheduleType":"3","ScheduleID":"2399282","PlayerName":"Moises Caicedo","PlayerID":"184564","PlayerID2":"0","PlayerName_J":"凯塞多"},{"Minute":"58","ClassType":"0","ScheduleType":"4","ScheduleID":"2399282","PlayerName":null,"PlayerID":null,"PlayerID2":"0","PlayerName_J":null},{"Minute":"60","ClassType":"1","ScheduleType":"4","ScheduleID":"2399282","PlayerName":null,"PlayerID":null,"PlayerID2":"0","PlayerName_J":null},{"Minute":"60","ClassType":"1","ScheduleType":"4","ScheduleID":"2399282","PlayerName":null,"PlayerID":null,"PlayerID2":"0","PlayerName_J":null},{"Minute":"63","ClassType":"0","ScheduleType":"1","ScheduleID":"2399282","PlayerName":"Matheus Cunha(Assists:Pedro Neto)","PlayerID":"155454","PlayerID2":"0","PlayerName_J":"库尼亚 (助攻:内托)"},{"Minute":"63","ClassType":"1","ScheduleType":"11","ScheduleID":"2399282","PlayerName":"Nicolas Jackson↑Moises Caicedo↓","PlayerID":"201058","PlayerID2":"0","PlayerName_J":"N·杰克逊↑凯塞多↓"},{"Minute":"72","ClassType":"1","ScheduleType":"11","ScheduleID":"2399282","PlayerName":"Mykhailo Mudryk↑Raheem Sterling↓","PlayerID":"198068","PlayerID2":"0","PlayerName_J":"穆德里克↑斯特林↓"},{"Minute":"72","ClassType":"1","ScheduleType":"11","ScheduleID":"2399282","PlayerName":"Carney Chukwuemeka↑Christopher Nkunku↓","PlayerID":"205667","PlayerID2":"0","PlayerName_J":"楚克乌梅卡↑恩昆库↓"},{"Minute":"72","ClassType":"0","ScheduleType":"11","ScheduleID":"2399282","PlayerName":"Jeanricner Bellegarde↑Pedro Neto↓","PlayerID":"145124","PlayerID2":"0","PlayerName_J":"贝雷格莱德↑内托↓"},{"Minute":"72","ClassType":"0","ScheduleType":"11","ScheduleID":"2399282","PlayerName":"Thomas Glyn Doyle↑Pablo Sarabia Garcia↓","PlayerID":"180961","PlayerID2":"0","PlayerName_J":"T.道尔↑萨拉维亚↓"},{"Minute":"78","ClassType":"1","ScheduleType":"3","ScheduleID":"2399282","PlayerName":"Benjamin Chilwell","PlayerID":"138923","PlayerID2":"0","PlayerName_J":"奇尔维尔"},{"Minute":"81","ClassType":"1","ScheduleType":"11","ScheduleID":"2399282","PlayerName":"Alfie Gilchrist↑Malo Gusto↓","PlayerID":"236978","PlayerID2":"0","PlayerName_J":"阿尔菲·吉尔克里斯特↑古斯托↓"},{"Minute":"81","ClassType":"1","ScheduleType":"11","ScheduleID":"2399282","PlayerName":"Benoit Badiashile Mukinayi↑Benjamin Chilwell↓","PlayerID":"170579","PlayerID2":"0","PlayerName_J":"贝迪亚沙尔↑奇尔维尔↓"},{"Minute":"82","ClassType":"0","ScheduleType":"7","ScheduleID":"2399282","PlayerName":"Matheus Cunha","PlayerID":"155454","PlayerID2":"0","PlayerName_J":"库尼亚"},{"Minute":"86","ClassType":"1","ScheduleType":"1","ScheduleID":"2399282","PlayerName":"Thiago Emiliano da Silva(Assists:Mykhailo Mudryk)","PlayerID":"65491","PlayerID2":"0","PlayerName_J":"席尔瓦 (助攻:穆德里克)"},{"Minute":"86","ClassType":"1","ScheduleType":"4","ScheduleID":"2399282","PlayerName":null,"PlayerID":null,"PlayerID2":"0","PlayerName_J":null},{"Minute":"87","ClassType":"0","ScheduleType":"11","ScheduleID":"2399282","PlayerName":"Hugo Bueno↑Rayan Ait Nouri↓","PlayerID":"219935","PlayerID2":"0","PlayerName_J":"晓高贝尔奴↑艾特努里↓"},{"Minute":"90","ClassType":"0","ScheduleType":"11","ScheduleID":"2399282","PlayerName":"Matt Doherty↑Joao Victor Gomes da Silva↓","PlayerID":"109496","PlayerID2":"0","PlayerName_J":"多赫蒂↑J.戈麦斯↓"},{"Minute":"90","ClassType":"1","ScheduleType":"4","ScheduleID":"2399282","PlayerName":null,"PlayerID":null,"PlayerID2":"0","PlayerName_J":null},{"Minute":"90","ClassType":"1","ScheduleType":"4","ScheduleID":"2399282","PlayerName":null,"PlayerID":null,"PlayerID2":"0","PlayerName_J":null}],"scheduleEventList":{"event_info":[],"technic":{"14":{"leixing":"14","home_info":"64%","away_info":"36%"},"46":{"leixing":"46","home_info":"60%","away_info":"40%"},"41":{"leixing":"41","home_info":"596","away_info":"345"},"5":{"leixing":"5","home_info":"15","away_info":"11"},"43":{"leixing":"43","home_info":"133","away_info":"65"},"42":{"leixing":"42","home_info":"89%","away_info":"80%"},"3":{"leixing":"3","home_info":"14","away_info":"15"},"4":{"leixing":"4","home_info":"5","away_info":"8"},"44":{"leixing":"44","home_info":"67","away_info":"31"},"45":{"leixing":"45","home_info":"3","away_info":"0"},"8":{"leixing":"8","home_info":"11","away_info":"14"},"16":{"leixing":"16","home_info":"2","away_info":"3"},"40":{"leixing":"40","home_info":"23","away_info":"18"},"6":{"leixing":"6","home_info":"9","away_info":"1"},"34":{"leixing":"34","home_info":"9","away_info":"7"},"39":{"leixing":"39","home_info":"10","away_info":"7"},"0":{"leixing":"0","home_info":"","away_info":"*"},"37":{"leixing":"37","home_info":"2","away_info":"3"},"38":{"leixing":"38","home_info":"12","away_info":"19"},"19":{"leixing":"19","home_info":"12","away_info":"19"},"20":{"leixing":"20","home_info":"7","away_info":"6"},"15":{"leixing":"15","home_info":"23","away_info":"15"},"36":{"leixing":"36","home_info":"11","away_info":"8"},"23":{"leixing":"23","home_info":"2","away_info":"2"},"11":{"leixing":"11","home_info":"3","away_info":"2"},"9":{"leixing":"9","home_info":"2","away_info":"0"}},"technicList":[{"leixing":"14","home_info":"64%","away_info":"36%"},{"leixing":"46","home_info":"60%","away_info":"40%"},{"leixing":"41","home_info":"596","away_info":"345"},{"leixing":"5","home_info":"15","away_info":"11"},{"leixing":"43","home_info":"133","away_info":"65"},{"leixing":"42","home_info":"89%","away_info":"80%"},{"leixing":"3","home_info":"14","away_info":"15"},{"leixing":"4","home_info":"5","away_info":"8"},{"leixing":"44","home_info":"67","away_info":"31"},{"leixing":"45","home_info":"3","away_info":"0"},{"leixing":"8","home_info":"11","away_info":"14"},{"leixing":"16","home_info":"2","away_info":"3"},{"leixing":"40","home_info":"23","away_info":"18"},{"leixing":"6","home_info":"9","away_info":"1"},{"leixing":"34","home_info":"9","away_info":"7"},{"leixing":"39","home_info":"10","away_info":"7"},{"leixing":"0","home_info":"","away_info":"*"},{"leixing":"37","home_info":"2","away_info":"3"},{"leixing":"38","home_info":"12","away_info":"19"},{"leixing":"19","home_info":"12","away_info":"19"},{"leixing":"20","home_info":"7","away_info":"6"},{"leixing":"15","home_info":"23","away_info":"15"},{"leixing":"36","home_info":"11","away_info":"8"},{"leixing":"23","home_info":"2","away_info":"2"},{"leixing":"11","home_info":"3","away_info":"2"},{"leixing":"9","home_info":"2","away_info":"0"}]},"o_odds":{"o_home_first":"1.57","o_stand_first":"4","o_guest_first":"6","o_home":"1.55","o_stand":"4.2","o_guest":"5.75","o_home_r":"501","o_stand_r":"51","o_guest_r":"1","modifyTime":"2024-02-04 23:59:05","closePan":""},"y_odds":{"y_first_goal":"-1.00","y_first_upOdds":"","y_first_downOdds":"","y_goal":"0.00","y_up":"0.50","y_down":"1.70","y_goal_r":"-1.00","y_up_r":"0.88","y_down_r":"1.02","modifyTime":"2024-02-04 23:59:16","closePan":""},"total_score_odds":{"first_total_score_goal":"2.75","first_total_score_upOdds":"0.95","first_total_score_downOdds":"0.95","total_score_goal":"6.5","total_score_up":"5.4","total_score_down":"0.12","total_score_goal_r":"3","total_score_upOdds_r":"1.01","total_score_downOdds_r":"0.89","modifyTime":"2024-02-04 23:59:16","closePan":""}},{"lightning":"0","hasAnalysis":0,"isCollect":0,"id":"2399284","matchId":"2399284","league":"英格兰超级联赛","leagueShort":"英超","leagueColor":"#FF3333","home":"曼彻斯特联","away":"西汉姆联","HomeTeamID":27,"GuestTeamID":62,"home_img":"https:\/\/images.footballant.com\/team\/27.png!webp","away_img":"https:\/\/images.footballant.com\/team\/62.png!webp","sclassID":"36","league_img":"https:\/\/images.footballant.com\/sclass\/36.png!webp","homeScore":3,"awayScore":0,"homeHalfScore":1,"awayHalfScore":0,"homered":0,"awayRed":0,"homeYellow":0,"awayYellow":1,"homeCorner":5,"guestCorner":8,"homeHalfCorner":2,"guestHalfCorner":4,"match_date":"02-04 22:00","match_time":"2024\/02\/04 22:00:00","match_time_timestamp":1707055200000,"state":"-1","explainList":"1;|;;;;","start_time":"2024\/02\/04 22:00:00","MatchTime2_timestamp":1707059087000,"start_time_timestamp":1707055200000,"event_list":[{"Minute":"11","ClassType":"0","ScheduleType":"4","ScheduleID":"2399284","PlayerName":null,"PlayerID":null,"PlayerID2":"0","PlayerName_J":null},{"Minute":"15","ClassType":"1","ScheduleType":"4","ScheduleID":"2399284","PlayerName":null,"PlayerID":null,"PlayerID2":"0","PlayerName_J":null},{"Minute":"15","ClassType":"1","ScheduleType":"4","ScheduleID":"2399284","PlayerName":null,"PlayerID":null,"PlayerID2":"0","PlayerName_J":null},{"Minute":"18","ClassType":"0","ScheduleType":"4","ScheduleID":"2399284","PlayerName":null,"PlayerID":null,"PlayerID2":"0","PlayerName_J":null},{"Minute":"23","ClassType":"1","ScheduleType":"1","ScheduleID":"2399284","PlayerName":"Rasmus Hojlund(Assists:Carlos Henrique Casimiro,Casemiro)","PlayerID":"201304","PlayerID2":"0","PlayerName_J":"R.霍伊伦德 (助攻:卡塞米罗)"},{"Minute":"26","ClassType":"0","ScheduleType":"4","ScheduleID":"2399284","PlayerName":null,"PlayerID":null,"PlayerID2":"0","PlayerName_J":null},{"Minute":"37","ClassType":"0","ScheduleType":"3","ScheduleID":"2399284","PlayerName":"Tomas Soucek","PlayerID":"134904","PlayerID2":"0","PlayerName_J":"绍切克"},{"Minute":"41","ClassType":"0","ScheduleType":"4","ScheduleID":"2399284","PlayerName":null,"PlayerID":null,"PlayerID2":"0","PlayerName_J":null},{"Minute":"46","ClassType":"0","ScheduleType":"11","ScheduleID":"2399284","PlayerName":"Lukasz Fabianski↑Alphonse Areola↓","PlayerID":"25037","PlayerID2":"0","PlayerName_J":"法比安斯基↑阿雷奥拉↓"},{"Minute":"49","ClassType":"1","ScheduleType":"1","ScheduleID":"2399284","PlayerName":"Alejandro Garnacho(Assists:Bruno Joao N. Borges Fernandes)","PlayerID":"220768","PlayerID2":"0","PlayerName_J":"A·加纳乔 (助攻:费尔南德斯)"},{"Minute":"53","ClassType":"0","ScheduleType":"4","ScheduleID":"2399284","PlayerName":null,"PlayerID":null,"PlayerID2":"0","PlayerName_J":null},{"Minute":"54","ClassType":"1","ScheduleType":"4","ScheduleID":"2399284","PlayerName":null,"PlayerID":null,"PlayerID2":"0","PlayerName_J":null},{"Minute":"64","ClassType":"1","ScheduleType":"11","ScheduleID":"2399284","PlayerName":"Scott Mctominay↑Kobbie Mainoo↓","PlayerID":"153040","PlayerID2":"0","PlayerName_J":"麦克托米奈↑科比·梅努↓"},{"Minute":"71","ClassType":"1","ScheduleType":"11","ScheduleID":"2399284","PlayerName":"Raphael Varane↑Lisandro Martinez↓","PlayerID":"79115","PlayerID2":"0","PlayerName_J":"瓦拉内↑L.马丁内斯↓"},{"Minute":"72","ClassType":"0","ScheduleType":"4","ScheduleID":"2399284","PlayerName":null,"PlayerID":null,"PlayerID2":"0","PlayerName_J":null},{"Minute":"72","ClassType":"0","ScheduleType":"11","ScheduleID":"2399284","PlayerName":"Gnaly Maxwell Cornet↑Tomas Soucek↓","PlayerID":"123832","PlayerID2":"0","PlayerName_J":"科尔内↑绍切克↓"},{"Minute":"72","ClassType":"0","ScheduleType":"11","ScheduleID":"2399284","PlayerName":"Kalvin Phillips↑Vladimir Coufal↓","PlayerID":"134688","PlayerID2":"0","PlayerName_J":"菲利普斯↑库法尔↓"},{"Minute":"77","ClassType":"0","ScheduleType":"4","ScheduleID":"2399284","PlayerName":null,"PlayerID":null,"PlayerID2":"0","PlayerName_J":null},{"Minute":"82","ClassType":"1","ScheduleType":"4","ScheduleID":"2399284","PlayerName":null,"PlayerID":null,"PlayerID2":"0","PlayerName_J":null},{"Minute":"83","ClassType":"1","ScheduleType":"4","ScheduleID":"2399284","PlayerName":null,"PlayerID":null,"PlayerID2":"0","PlayerName_J":null},{"Minute":"84","ClassType":"1","ScheduleType":"1","ScheduleID":"2399284","PlayerName":"Alejandro Garnacho(Assists:Scott Mctominay)","PlayerID":"220768","PlayerID2":"0","PlayerName_J":"A·加纳乔 (助攻:麦克托米奈)"},{"Minute":"88","ClassType":"1","ScheduleType":"11","ScheduleID":"2399284","PlayerName":"Victor Nilsson-Lindelof↑Luke Shaw↓","PlayerID":"82932","PlayerID2":"0","PlayerName_J":"林德洛夫↑肖↓"},{"Minute":"88","ClassType":"1","ScheduleType":"11","ScheduleID":"2399284","PlayerName":"Antony Matheus dos Santos↑Rasmus Hojlund↓","PlayerID":"173359","PlayerID2":"0","PlayerName_J":"安东尼↑R.霍伊伦德↓"},{"Minute":"90","ClassType":"0","ScheduleType":"4","ScheduleID":"2399284","PlayerName":null,"PlayerID":null,"PlayerID2":"0","PlayerName_J":null}],"scheduleEventList":{"event_info":[],"technic":{"14":{"leixing":"14","home_info":"51%","away_info":"49%"},"46":{"leixing":"46","home_info":"54%","away_info":"46%"},"41":{"leixing":"41","home_info":"515","away_info":"456"},"42":{"leixing":"42","home_info":"85%","away_info":"87%"},"5":{"leixing":"5","home_info":"10","away_info":"5"},"38":{"leixing":"38","home_info":"18","away_info":"16"},"39":{"leixing":"39","home_info":"7","away_info":"13"},"43":{"leixing":"43","home_info":"97","away_info":"99"},"8":{"leixing":"8","home_info":"5","away_info":"11"},"20":{"leixing":"20","home_info":"4","away_info":"10"},"44":{"leixing":"44","home_info":"46","away_info":"66"},"40":{"leixing":"40","home_info":"13","away_info":"18"},"0":{"leixing":"0","home_info":"*","away_info":""},"45":{"leixing":"45","home_info":"2","away_info":"4"},"15":{"leixing":"15","home_info":"18","away_info":"22"},"36":{"leixing":"36","home_info":"12","away_info":"8"},"6":{"leixing":"6","home_info":"5","away_info":"8"},"3":{"leixing":"3","home_info":"12","away_info":"21"},"34":{"leixing":"34","home_info":"7","away_info":"18"},"16":{"leixing":"16","home_info":"3","away_info":"2"},"19":{"leixing":"19","home_info":"18","away_info":"16"},"37":{"leixing":"37","home_info":"2","away_info":"7"},"4":{"leixing":"4","home_info":"5","away_info":"3"},"23":{"leixing":"23","home_info":"3","away_info":"0"},"11":{"leixing":"11","home_info":"0","away_info":"1"},"9":{"leixing":"9","home_info":"1","away_info":"0"}},"technicList":[{"leixing":"14","home_info":"51%","away_info":"49%"},{"leixing":"46","home_info":"54%","away_info":"46%"},{"leixing":"41","home_info":"515","away_info":"456"},{"leixing":"42","home_info":"85%","away_info":"87%"},{"leixing":"5","home_info":"10","away_info":"5"},{"leixing":"38","home_info":"18","away_info":"16"},{"leixing":"39","home_info":"7","away_info":"13"},{"leixing":"43","home_info":"97","away_info":"99"},{"leixing":"8","home_info":"5","away_info":"11"},{"leixing":"20","home_info":"4","away_info":"10"},{"leixing":"44","home_info":"46","away_info":"66"},{"leixing":"40","home_info":"13","away_info":"18"},{"leixing":"0","home_info":"*","away_info":""},{"leixing":"45","home_info":"2","away_info":"4"},{"leixing":"15","home_info":"18","away_info":"22"},{"leixing":"36","home_info":"12","away_info":"8"},{"leixing":"6","home_info":"5","away_info":"8"},{"leixing":"3","home_info":"12","away_info":"21"},{"leixing":"34","home_info":"7","away_info":"18"},{"leixing":"16","home_info":"3","away_info":"2"},{"leixing":"19","home_info":"18","away_info":"16"},{"leixing":"37","home_info":"2","away_info":"7"},{"leixing":"4","home_info":"5","away_info":"3"},{"leixing":"23","home_info":"3","away_info":"0"},{"leixing":"11","home_info":"0","away_info":"1"},{"leixing":"9","home_info":"1","away_info":"0"}]},"o_odds":{"o_home_first":"1.75","o_stand_first":"4","o_guest_first":"4.2","o_home":"1.55","o_stand":"4.33","o_guest":"5.5","o_home_r":"1","o_stand_r":"26","o_guest_r":"101","modifyTime":"2024-02-04 23:42:58","closePan":""},"y_odds":{"y_first_goal":"-0.75","y_first_upOdds":"","y_first_downOdds":"","y_goal":"0.00","y_up":"0.62","y_down":"1.40","y_goal_r":"-1.00","y_up_r":"0.89","y_down_r":"1.01","modifyTime":"2024-02-04 23:53:16","closePan":""},"total_score_odds":{"first_total_score_goal":"3","first_total_score_upOdds":"1.02","first_total_score_downOdds":"0.88","total_score_goal":"3.5","total_score_up":"7.3","total_score_down":"0.08","total_score_goal_r":"3","total_score_upOdds_r":"1","total_score_downOdds_r":"0.9","modifyTime":"2024-02-04 23:53:16","closePan":""}},{"lightning":"0","hasAnalysis":0,"isCollect":0,"id":"2399286","matchId":"2399286","league":"英格兰超级联赛","leagueShort":"英超","leagueColor":"#FF3333","home":"谢菲尔德联队","away":"阿斯顿维拉","HomeTeamID":51,"GuestTeamID":20,"home_img":"https:\/\/images.footballant.com\/team\/51.png!webp","away_img":"https:\/\/images.footballant.com\/team\/20.png!webp","sclassID":"36","league_img":"https:\/\/images.footballant.com\/sclass\/36.png!webp","homeScore":0,"awayScore":5,"homeHalfScore":0,"awayHalfScore":4,"homered":0,"awayRed":0,"homeYellow":1,"awayYellow":0,"homeCorner":3,"guestCorner":4,"homeHalfCorner":0,"guestHalfCorner":3,"match_date":"02-04 01:30","match_time":"2024\/02\/04 01:30:00","match_time_timestamp":1706981400000,"state":"-1","explainList":"2;|;;;;","start_time":"2024\/02\/04 01:30:00","MatchTime2_timestamp":1706985327000,"start_time_timestamp":1706981400000,"event_list":[{"Minute":"12","ClassType":"0","ScheduleType":"1","ScheduleID":"2399286","PlayerName":"John McGinn","PlayerID":"101962","PlayerID2":"0","PlayerName_J":"麦克金"},{"Minute":"16","ClassType":"0","ScheduleType":"1","ScheduleID":"2399286","PlayerName":"Ollie Watkins(Assists:Douglas Luiz Soares de Paulo)","PlayerID":"126024","PlayerID2":"0","PlayerName_J":"沃特金斯 (助攻:路易斯)"},{"Minute":"20","ClassType":"0","ScheduleType":"1","ScheduleID":"2399286","PlayerName":"Leon Bailey(Assists:Ollie Watkins)","PlayerID":"136110","PlayerID2":"0","PlayerName_J":"贝利 (助攻:沃特金斯)"},{"Minute":"26","ClassType":"0","ScheduleType":"4","ScheduleID":"2399286","PlayerName":null,"PlayerID":null,"PlayerID2":"0","PlayerName_J":null},{"Minute":"29","ClassType":"0","ScheduleType":"4","ScheduleID":"2399286","PlayerName":null,"PlayerID":null,"PlayerID2":"0","PlayerName_J":null},{"Minute":"30","ClassType":"0","ScheduleType":"1","ScheduleID":"2399286","PlayerName":"Youri Tielemans","PlayerID":"116360","PlayerID2":"0","PlayerName_J":"蒂莱曼斯"},{"Minute":"30","ClassType":"0","ScheduleType":"4","ScheduleID":"2399286","PlayerName":null,"PlayerID":null,"PlayerID2":"0","PlayerName_J":null},{"Minute":"44","ClassType":"1","ScheduleType":"3","ScheduleID":"2399286","PlayerName":"Jayden Bogle","PlayerID":"163508","PlayerID2":"0","PlayerName_J":"博格尔"},{"Minute":"46","ClassType":"1","ScheduleType":"11","ScheduleID":"2399286","PlayerName":"Gustavo Hamer↑William Osula↓","PlayerID":"145589","PlayerID2":"0","PlayerName_J":"G.哈默尔↑威廉·奥苏拉↓"},{"Minute":"46","ClassType":"0","ScheduleType":"11","ScheduleID":"2399286","PlayerName":"Jacob Ramsey↑Douglas Luiz Soares de Paulo↓","PlayerID":"172520","PlayerID2":"0","PlayerName_J":"拉姆塞↑路易斯↓"},{"Minute":"47","ClassType":"0","ScheduleType":"1","ScheduleID":"2399286","PlayerName":"Alexandre Moreno Lopera(Assists:Ollie Watkins)","PlayerID":"115911","PlayerID2":"0","PlayerName_J":"莫雷诺 (助攻:沃特金斯)"},{"Minute":"50","ClassType":"1","ScheduleType":"11","ScheduleID":"2399286","PlayerName":"Ben Osborne↑Andrew Brooks↓","PlayerID":"118321","PlayerID2":"0","PlayerName_J":"奥斯伯恩↑安德鲁·布鲁克斯↓"},{"Minute":"50","ClassType":"1","ScheduleType":"11","ScheduleID":"2399286","PlayerName":"Jack Robinson↑Rhys Norrington-Davies↓","PlayerID":"77293","PlayerID2":"0","PlayerName_J":"罗宾逊↑戴维斯↓"},{"Minute":"59","ClassType":"0","ScheduleType":"4","ScheduleID":"2399286","PlayerName":null,"PlayerID":null,"PlayerID2":"0","PlayerName_J":null},{"Minute":"59","ClassType":"0","ScheduleType":"11","ScheduleID":"2399286","PlayerName":"Matthew Cash↑Ezri Konsa Ngoyo↓","PlayerID":"145445","PlayerID2":"0","PlayerName_J":"卡斯↑孔萨↓"},{"Minute":"60","ClassType":"0","ScheduleType":"11","ScheduleID":"2399286","PlayerName":"Moussa Diaby↑Leon Bailey↓","PlayerID":"162774","PlayerID2":"0","PlayerName_J":"迪亚比↑贝利↓"},{"Minute":"65","ClassType":"1","ScheduleType":"11","ScheduleID":"2399286","PlayerName":"Cameron Archer↑Ben Brereton↓","PlayerID":"181585","PlayerID2":"0","PlayerName_J":"C.阿切尔↑布里尔顿↓"},{"Minute":"71","ClassType":"0","ScheduleType":"11","ScheduleID":"2399286","PlayerName":"Tim Iroegbunam↑John McGinn↓","PlayerID":"213272","PlayerID2":"0","PlayerName_J":"蒂姆·伊罗格布纳↑麦克金↓"},{"Minute":"72","ClassType":"1","ScheduleType":"11","ScheduleID":"2399286","PlayerName":"Thomas Davies↑James Mcatee↓","PlayerID":"143098","PlayerID2":"0","PlayerName_J":"戴维斯↑麦卡蒂↓"},{"Minute":"77","ClassType":"1","ScheduleType":"4","ScheduleID":"2399286","PlayerName":null,"PlayerID":null,"PlayerID2":"0","PlayerName_J":null},{"Minute":"78","ClassType":"1","ScheduleType":"4","ScheduleID":"2399286","PlayerName":null,"PlayerID":null,"PlayerID2":"0","PlayerName_J":null},{"Minute":"81","ClassType":"0","ScheduleType":"11","ScheduleID":"2399286","PlayerName":"Morgan Rogers↑Youri Tielemans↓","PlayerID":"172381","PlayerID2":"0","PlayerName_J":"M.罗杰斯↑蒂莱曼斯↓"},{"Minute":"90","ClassType":"1","ScheduleType":"4","ScheduleID":"2399286","PlayerName":null,"PlayerID":null,"PlayerID2":"0","PlayerName_J":null},{"Minute":"90","ClassType":"1","ScheduleType":"14","ScheduleID":"2399286","PlayerName":"Vini Souza(Reason:Goal Disallowed)","PlayerID":"258257","PlayerID2":"0","PlayerName_J":"V.苏赛 (原因:进球无效)"}],"scheduleEventList":{"event_info":[],"technic":{"14":{"leixing":"14","home_info":"34%","away_info":"66%"},"46":{"leixing":"46","home_info":"29%","away_info":"71%"},"43":{"leixing":"43","home_info":"76","away_info":"103"},"8":{"leixing":"8","home_info":"7","away_info":"16"},"41":{"leixing":"41","home_info":"328","away_info":"629"},"36":{"leixing":"36","home_info":"8","away_info":"13"},"42":{"leixing":"42","home_info":"78%","away_info":"89%"},"5":{"leixing":"5","home_info":"10","away_info":"7"},"15":{"leixing":"15","home_info":"24","away_info":"18"},"44":{"leixing":"44","home_info":"30","away_info":"34"},"20":{"leixing":"20","home_info":"8","away_info":"7"},"0":{"leixing":"0","home_info":"","away_info":"*"},"38":{"leixing":"38","home_info":"16","away_info":"7"},"3":{"leixing":"3","home_info":"10","away_info":"14"},"34":{"leixing":"34","home_info":"5","away_info":"4"},"4":{"leixing":"4","home_info":"5","away_info":"10"},"16":{"leixing":"16","home_info":"5","away_info":"5"},"39":{"leixing":"39","home_info":"9","away_info":"11"},"40":{"leixing":"40","home_info":"14","away_info":"17"},"19":{"leixing":"19","home_info":"16","away_info":"7"},"9":{"leixing":"9","home_info":"6","away_info":"0"},"23":{"leixing":"23","home_info":"0","away_info":"3"},"6":{"leixing":"6","home_info":"3","away_info":"4"},"45":{"leixing":"45","home_info":"0","away_info":"3"},"11":{"leixing":"11","home_info":"1","away_info":"0"},"37":{"leixing":"37","home_info":"3","away_info":"0"}},"technicList":[{"leixing":"14","home_info":"34%","away_info":"66%"},{"leixing":"46","home_info":"29%","away_info":"71%"},{"leixing":"43","home_info":"76","away_info":"103"},{"leixing":"8","home_info":"7","away_info":"16"},{"leixing":"41","home_info":"328","away_info":"629"},{"leixing":"36","home_info":"8","away_info":"13"},{"leixing":"42","home_info":"78%","away_info":"89%"},{"leixing":"5","home_info":"10","away_info":"7"},{"leixing":"15","home_info":"24","away_info":"18"},{"leixing":"44","home_info":"30","away_info":"34"},{"leixing":"20","home_info":"8","away_info":"7"},{"leixing":"0","home_info":"","away_info":"*"},{"leixing":"38","home_info":"16","away_info":"7"},{"leixing":"3","home_info":"10","away_info":"14"},{"leixing":"34","home_info":"5","away_info":"4"},{"leixing":"4","home_info":"5","away_info":"10"},{"leixing":"16","home_info":"5","away_info":"5"},{"leixing":"39","home_info":"9","away_info":"11"},{"leixing":"40","home_info":"14","away_info":"17"},{"leixing":"19","home_info":"16","away_info":"7"},{"leixing":"9","home_info":"6","away_info":"0"},{"leixing":"23","home_info":"0","away_info":"3"},{"leixing":"6","home_info":"3","away_info":"4"},{"leixing":"45","home_info":"0","away_info":"3"},{"leixing":"11","home_info":"1","away_info":"0"},{"leixing":"37","home_info":"3","away_info":"0"}]},"o_odds":{"o_home_first":"6","o_stand_first":"4.5","o_guest_first":"1.5","o_home":"5","o_stand":"4.2","o_guest":"1.61","o_home_r":"126","o_stand_r":"51","o_guest_r":"1","modifyTime":"2024-02-04 02:04:17","closePan":""},"y_odds":{"y_first_goal":"1.00","y_first_upOdds":"","y_first_downOdds":"","y_goal":"0.00","y_up":"1.35","y_down":"0.65","y_goal_r":"1.00","y_up_r":"0.83","y_down_r":"1.07","modifyTime":"2024-02-04 03:24:03","closePan":""},"total_score_odds":{"first_total_score_goal":"3","first_total_score_upOdds":"1.03","first_total_score_downOdds":"0.87","total_score_goal":"5.5","total_score_up":"8","total_score_down":"0.07","total_score_goal_r":"2.75","total_score_upOdds_r":"0.86","total_score_downOdds_r":"1.04","modifyTime":"2024-02-04 03:24:03","closePan":""}},{"lightning":"0","hasAnalysis":0,"isCollect":0,"id":"2399280","matchId":"2399280","league":"英格兰超级联赛","leagueShort":"英超","leagueColor":"#FF3333","home":"布莱顿","away":"水晶宫","HomeTeamID":60,"GuestTeamID":35,"home_img":"https:\/\/images.footballant.com\/team\/60.png!webp","away_img":"https:\/\/images.footballant.com\/team\/35.png!webp","sclassID":"36","league_img":"https:\/\/images.footballant.com\/sclass\/36.png!webp","homeScore":4,"awayScore":1,"homeHalfScore":3,"awayHalfScore":0,"homered":0,"awayRed":0,"homeYellow":1,"awayYellow":3,"homeCorner":3,"guestCorner":2,"homeHalfCorner":1,"guestHalfCorner":1,"match_date":"02-03 23:00","match_time":"2024\/02\/03 23:00:00","match_time_timestamp":1706972400000,"state":"-1","explainList":"2;|;;;;","start_time":"2024\/02\/03 23:00:00","MatchTime2_timestamp":1706976411000,"start_time_timestamp":1706972400000,"event_list":[{"Minute":"3","ClassType":"1","ScheduleType":"4","ScheduleID":"2399280","PlayerName":null,"PlayerID":null,"PlayerID2":"0","PlayerName_J":null},{"Minute":"3","ClassType":"1","ScheduleType":"1","ScheduleID":"2399280","PlayerName":"Lewis Dunk(Assists:Pascal Gross)","PlayerID":"79361","PlayerID2":"0","PlayerName_J":"邓克 (助攻:格罗斯)"},{"Minute":"16","ClassType":"0","ScheduleType":"3","ScheduleID":"2399280","PlayerName":"Marc Guehi","PlayerID":"175796","PlayerID2":"0","PlayerName_J":"格伊"},{"Minute":"28","ClassType":"0","ScheduleType":"11","ScheduleID":"2399280","PlayerName":"Adam Wharton↑Marc Guehi↓","PlayerID":"222241","PlayerID2":"0","PlayerName_J":"沃顿↑格伊↓"},{"Minute":"33","ClassType":"1","ScheduleType":"1","ScheduleID":"2399280","PlayerName":"Jack Hinshelwood(Assists:Tariq Lamptey)","PlayerID":"231704","PlayerID2":"0","PlayerName_J":"J.辛舍伍德 (助攻:兰普泰)"},{"Minute":"34","ClassType":"1","ScheduleType":"1","ScheduleID":"2399280","PlayerName":"Facundo Buonanotte(Assists:Pascal Gross)","PlayerID":"222609","PlayerID2":"0","PlayerName_J":"法孔多布诺特 (助攻:格罗斯)"},{"Minute":"45","ClassType":"0","ScheduleType":"4","ScheduleID":"2399280","PlayerName":null,"PlayerID":null,"PlayerID2":"0","PlayerName_J":null},{"Minute":"46","ClassType":"0","ScheduleType":"11","ScheduleID":"2399280","PlayerName":"Michael Olise↑Jeffrey Schlupp↓","PlayerID":"173412","PlayerID2":"0","PlayerName_J":"奥利斯↑施卢普↓"},{"Minute":"50","ClassType":"0","ScheduleType":"4","ScheduleID":"2399280","PlayerName":null,"PlayerID":null,"PlayerID2":"0","PlayerName_J":null},{"Minute":"54","ClassType":"1","ScheduleType":"4","ScheduleID":"2399280","PlayerName":null,"PlayerID":null,"PlayerID2":"0","PlayerName_J":null},{"Minute":"56","ClassType":"0","ScheduleType":"11","ScheduleID":"2399280","PlayerName":"Matheus Franca de Oliveira↑Michael Olise↓","PlayerID":"220722","PlayerID2":"0","PlayerName_J":"M.弗朗卡↑奥利斯↓"},{"Minute":"59","ClassType":"0","ScheduleType":"3","ScheduleID":"2399280","PlayerName":"Matheus Franca de Oliveira","PlayerID":"220722","PlayerID2":"0","PlayerName_J":"M.弗朗卡"},{"Minute":"62","ClassType":"0","ScheduleType":"3","ScheduleID":"2399280","PlayerName":"Daniel Munoz","PlayerID":"151105","PlayerID2":"0","PlayerName_J":"穆诺斯"},{"Minute":"69","ClassType":"1","ScheduleType":"11","ScheduleID":"2399280","PlayerName":"Danny Welbeck↑Evan Ferguson↓","PlayerID":"28095","PlayerID2":"0","PlayerName_J":"维尔贝克↑埃文·弗格森↓"},{"Minute":"71","ClassType":"0","ScheduleType":"1","ScheduleID":"2399280","PlayerName":"Jean Philippe Mateta(Assists:Joachim Andersen)","PlayerID":"146759","PlayerID2":"0","PlayerName_J":"J.P.马泰塔 (助攻:安德森)"},{"Minute":"80","ClassType":"1","ScheduleType":"11","ScheduleID":"2399280","PlayerName":"Carlos Baleba↑Facundo Buonanotte↓","PlayerID":"224696","PlayerID2":"0","PlayerName_J":"卡洛斯·巴莱巴↑法孔多布诺特↓"},{"Minute":"80","ClassType":"1","ScheduleType":"11","ScheduleID":"2399280","PlayerName":"Pervis Josue Estupinan Tenorio↑Tariq Lamptey↓","PlayerID":"138408","PlayerID2":"0","PlayerName_J":"P·埃斯图皮尼安↑兰普泰↓"},{"Minute":"80","ClassType":"0","ScheduleType":"11","ScheduleID":"2399280","PlayerName":"Odsonne Edouard↑Jean Philippe Mateta↓","PlayerID":"138786","PlayerID2":"0","PlayerName_J":"爱德华↑J.P.马泰塔↓"},{"Minute":"80","ClassType":"0","ScheduleType":"11","ScheduleID":"2399280","PlayerName":"Naouirou Ahamada↑Will Hughes↓","PlayerID":"201690","PlayerID2":"0","PlayerName_J":"纳乌鲁·阿哈马达↑休斯↓"},{"Minute":"85","ClassType":"1","ScheduleType":"1","ScheduleID":"2399280","PlayerName":"João Pedro Junqueira de Jesus(Assists:Danny Welbeck)","PlayerID":"173371","PlayerID2":"0","PlayerName_J":"佩德罗 (助攻:维尔贝克)"},{"Minute":"88","ClassType":"1","ScheduleType":"11","ScheduleID":"2399280","PlayerName":"Anssumane Fati↑Igor Julio dos Santos de Paulo↓","PlayerID":"179216","PlayerID2":"0","PlayerName_J":"法蒂↑伊戈尔↓"},{"Minute":"88","ClassType":"1","ScheduleType":"11","ScheduleID":"2399280","PlayerName":"Adam Lallana↑João Pedro Junqueira de Jesus↓","PlayerID":"65429","PlayerID2":"0","PlayerName_J":"拉拉纳↑佩德罗↓"},{"Minute":"90","ClassType":"1","ScheduleType":"3","ScheduleID":"2399280","PlayerName":"Danny Welbeck","PlayerID":"28095","PlayerID2":"0","PlayerName_J":"维尔贝克"},{"Minute":"90","ClassType":"1","ScheduleType":"4","ScheduleID":"2399280","PlayerName":null,"PlayerID":null,"PlayerID2":"0","PlayerName_J":null}],"scheduleEventList":{"event_info":[],"technic":{"14":{"leixing":"14","home_info":"69%","away_info":"31%"},"46":{"leixing":"46","home_info":"75%","away_info":"25%"},"43":{"leixing":"43","home_info":"117","away_info":"77"},"6":{"leixing":"6","home_info":"3","away_info":"2"},"45":{"leixing":"45","home_info":"1","away_info":"1"},"3":{"leixing":"3","home_info":"13","away_info":"7"},"4":{"leixing":"4","home_info":"6","away_info":"5"},"41":{"leixing":"41","home_info":"837","away_info":"368"},"42":{"leixing":"42","home_info":"94%","away_info":"84%"},"39":{"leixing":"39","home_info":"8","away_info":"6"},"20":{"leixing":"20","home_info":"11","away_info":"13"},"15":{"leixing":"15","home_info":"9","away_info":"5"},"36":{"leixing":"36","home_info":"5","away_info":"2"},"5":{"leixing":"5","home_info":"7","away_info":"14"},"38":{"leixing":"38","home_info":"21","away_info":"16"},"40":{"leixing":"40","home_info":"15","away_info":"19"},"19":{"leixing":"19","home_info":"20","away_info":"16"},"23":{"leixing":"23","home_info":"4","away_info":"1"},"44":{"leixing":"44","home_info":"31","away_info":"21"},"8":{"leixing":"8","home_info":"15","away_info":"6"},"0":{"leixing":"0","home_info":"","away_info":"*"},"16":{"leixing":"16","home_info":"3","away_info":"2"},"11":{"leixing":"11","home_info":"1","away_info":"3"},"34":{"leixing":"34","home_info":"7","away_info":"2"},"37":{"leixing":"37","home_info":"6","away_info":"1"},"9":{"leixing":"9","home_info":"2","away_info":"2"}},"technicList":[{"leixing":"14","home_info":"69%","away_info":"31%"},{"leixing":"46","home_info":"75%","away_info":"25%"},{"leixing":"43","home_info":"117","away_info":"77"},{"leixing":"6","home_info":"3","away_info":"2"},{"leixing":"45","home_info":"1","away_info":"1"},{"leixing":"3","home_info":"13","away_info":"7"},{"leixing":"4","home_info":"6","away_info":"5"},{"leixing":"41","home_info":"837","away_info":"368"},{"leixing":"42","home_info":"94%","away_info":"84%"},{"leixing":"39","home_info":"8","away_info":"6"},{"leixing":"20","home_info":"11","away_info":"13"},{"leixing":"15","home_info":"9","away_info":"5"},{"leixing":"36","home_info":"5","away_info":"2"},{"leixing":"5","home_info":"7","away_info":"14"},{"leixing":"38","home_info":"21","away_info":"16"},{"leixing":"40","home_info":"15","away_info":"19"},{"leixing":"19","home_info":"20","away_info":"16"},{"leixing":"23","home_info":"4","away_info":"1"},{"leixing":"44","home_info":"31","away_info":"21"},{"leixing":"8","home_info":"15","away_info":"6"},{"leixing":"0","home_info":"","away_info":"*"},{"leixing":"16","home_info":"3","away_info":"2"},{"leixing":"11","home_info":"1","away_info":"3"},{"leixing":"34","home_info":"7","away_info":"2"},{"leixing":"37","home_info":"6","away_info":"1"},{"leixing":"9","home_info":"2","away_info":"2"}]},"o_odds":{"o_home_first":"1.65","o_stand_first":"4","o_guest_first":"5","o_home":"1.7","o_stand":"3.8","o_guest":"5","o_home_r":"1","o_stand_r":"41","o_guest_r":"301","modifyTime":"2024-02-04 00:46:14","closePan":""},"y_odds":{"y_first_goal":"-0.75","y_first_upOdds":"","y_first_downOdds":"","y_goal":"0.00","y_up":"0.67","y_down":"1.30","y_goal_r":"-0.75","y_up_r":"0.95","y_down_r":"0.95","modifyTime":"2024-02-04 00:53:48","closePan":""},"total_score_odds":{"first_total_score_goal":"2.75","first_total_score_upOdds":"0.95","first_total_score_downOdds":"0.95","total_score_goal":"5.5","total_score_up":"9.5","total_score_down":"0.05","total_score_goal_r":"2.5","total_score_upOdds_r":"1.06","total_score_downOdds_r":"0.84","modifyTime":"2024-02-04 00:53:48","closePan":""}},{"lightning":"0","hasAnalysis":0,"isCollect":0,"id":"2399281","matchId":"2399281","league":"英格兰超级联赛","leagueShort":"英超","leagueColor":"#FF3333","home":"伯恩利","away":"富勒姆","HomeTeamID":46,"GuestTeamID":29,"home_img":"https:\/\/images.footballant.com\/team\/46.png!webp","away_img":"https:\/\/images.footballant.com\/team\/29.png!webp","sclassID":"36","league_img":"https:\/\/images.footballant.com\/sclass\/36.png!webp","homeScore":2,"awayScore":2,"homeHalfScore":0,"awayHalfScore":2,"homered":0,"awayRed":0,"homeYellow":2,"awayYellow":2,"homeCorner":2,"guestCorner":13,"homeHalfCorner":2,"guestHalfCorner":3,"match_date":"02-03 23:00","match_time":"2024\/02\/03 23:00:00","match_time_timestamp":1706972400000,"state":"-1","explainList":"1;|;;;;","start_time":"2024\/02\/03 23:00:00","MatchTime2_timestamp":1706976249000,"start_time_timestamp":1706972400000,"event_list":[{"Minute":"5","ClassType":"1","ScheduleType":"4","ScheduleID":"2399281","PlayerName":null,"PlayerID":null,"PlayerID2":"0","PlayerName_J":null},{"Minute":"15","ClassType":"1","ScheduleType":"4","ScheduleID":"2399281","PlayerName":null,"PlayerID":null,"PlayerID2":"0","PlayerName_J":null},{"Minute":"16","ClassType":"0","ScheduleType":"4","ScheduleID":"2399281","PlayerName":null,"PlayerID":null,"PlayerID2":"0","PlayerName_J":null},{"Minute":"17","ClassType":"0","ScheduleType":"1","ScheduleID":"2399281","PlayerName":"Joao Palhinha(Assists:Andreas Hugo Hoelgebaum Pereira)","PlayerID":"135348","PlayerID2":"0","PlayerName_J":"帕利尼亚 (助攻:佩雷拉)"},{"Minute":"17","ClassType":"0","ScheduleType":"4","ScheduleID":"2399281","PlayerName":null,"PlayerID":null,"PlayerID2":"0","PlayerName_J":null},{"Minute":"21","ClassType":"0","ScheduleType":"1","ScheduleID":"2399281","PlayerName":"Rodrigo Muniz Carvalho(Assists:Antonee Robinson)","PlayerID":"200429","PlayerID2":"0","PlayerName_J":"卡瓦略 (助攻:A.罗宾逊)"},{"Minute":"35","ClassType":"0","ScheduleType":"4","ScheduleID":"2399281","PlayerName":null,"PlayerID":null,"PlayerID2":"0","PlayerName_J":null},{"Minute":"43","ClassType":"0","ScheduleType":"3","ScheduleID":"2399281","PlayerName":"Harrison Reed","PlayerID":"116595","PlayerID2":"0","PlayerName_J":"里德"},{"Minute":"45","ClassType":"0","ScheduleType":"3","ScheduleID":"2399281","PlayerName":"Andreas Hugo Hoelgebaum Pereira","PlayerID":"125060","PlayerID2":"0","PlayerName_J":"佩雷拉"},{"Minute":"46","ClassType":"1","ScheduleType":"11","ScheduleID":"2399281","PlayerName":"Maxime Esteve↑Hjalmar Ekdal↓","PlayerID":"209926","PlayerID2":"0","PlayerName_J":"埃斯特維↑埃克达尔↓"},{"Minute":"53","ClassType":"0","ScheduleType":"4","ScheduleID":"2399281","PlayerName":null,"PlayerID":null,"PlayerID2":"0","PlayerName_J":null},{"Minute":"54","ClassType":"0","ScheduleType":"4","ScheduleID":"2399281","PlayerName":null,"PlayerID":null,"PlayerID2":"0","PlayerName_J":null},{"Minute":"56","ClassType":"0","ScheduleType":"4","ScheduleID":"2399281","PlayerName":null,"PlayerID":null,"PlayerID2":"0","PlayerName_J":null},{"Minute":"56","ClassType":"0","ScheduleType":"4","ScheduleID":"2399281","PlayerName":null,"PlayerID":null,"PlayerID2":"0","PlayerName_J":null},{"Minute":"57","ClassType":"0","ScheduleType":"4","ScheduleID":"2399281","PlayerName":null,"PlayerID":null,"PlayerID2":"0","PlayerName_J":null},{"Minute":"63","ClassType":"0","ScheduleType":"4","ScheduleID":"2399281","PlayerName":null,"PlayerID":null,"PlayerID2":"0","PlayerName_J":null},{"Minute":"64","ClassType":"1","ScheduleType":"11","ScheduleID":"2399281","PlayerName":"David Datro Fofana↑Zeki Amdouni↓","PlayerID":"205322","PlayerID2":"0","PlayerName_J":"科芬拿↑Z.安杜尼↓"},{"Minute":"64","ClassType":"1","ScheduleType":"11","ScheduleID":"2399281","PlayerName":"Johann Berg Gudmundsson↑Aaron Ramsey↓","PlayerID":"42066","PlayerID2":"0","PlayerName_J":"格维兹门松↑拉姆塞↓"},{"Minute":"70","ClassType":"0","ScheduleType":"4","ScheduleID":"2399281","PlayerName":null,"PlayerID":null,"PlayerID2":"0","PlayerName_J":null},{"Minute":"70","ClassType":"0","ScheduleType":"4","ScheduleID":"2399281","PlayerName":null,"PlayerID":null,"PlayerID2":"0","PlayerName_J":null},{"Minute":"71","ClassType":"1","ScheduleType":"1","ScheduleID":"2399281","PlayerName":"David Datro Fofana(Assists:Lorenz Assignon)","PlayerID":"205322","PlayerID2":"0","PlayerName_J":"科芬拿 (助攻:阿斯格昂)"},{"Minute":"74","ClassType":"0","ScheduleType":"11","ScheduleID":"2399281","PlayerName":"Armando Broja↑Rodrigo Muniz Carvalho↓","PlayerID":"182754","PlayerID2":"0","PlayerName_J":"阿曼多·布罗亚↑卡瓦略↓"},{"Minute":"74","ClassType":"0","ScheduleType":"11","ScheduleID":"2399281","PlayerName":"Tom Cairney↑Bobby Reid↓","PlayerID":"69589","PlayerID2":"0","PlayerName_J":"凯尔尼↑雷德↓"},{"Minute":"80","ClassType":"0","ScheduleType":"4","ScheduleID":"2399281","PlayerName":null,"PlayerID":null,"PlayerID2":"0","PlayerName_J":null},{"Minute":"84","ClassType":"1","ScheduleType":"3","ScheduleID":"2399281","PlayerName":"Sander Berge","PlayerID":"130850","PlayerID2":"0","PlayerName_J":"伯格"},{"Minute":"85","ClassType":"0","ScheduleType":"11","ScheduleID":"2399281","PlayerName":"Kenny Tete↑Andreas Hugo Hoelgebaum Pereira↓","PlayerID":"120810","PlayerID2":"0","PlayerName_J":"泰迪↑佩雷拉↓"},{"Minute":"87","ClassType":"1","ScheduleType":"11","ScheduleID":"2399281","PlayerName":"Jacob Bruun Larsen↑Victor Alexander da Silva,Vitinho↓","PlayerID":"144961","PlayerID2":"0","PlayerName_J":"拉尔森↑维蒂尼奥↓"},{"Minute":"90","ClassType":"1","ScheduleType":"11","ScheduleID":"2399281","PlayerName":"Han-Noah Massengo↑Lorenz Assignon↓","PlayerID":"170737","PlayerID2":"0","PlayerName_J":"汉诺亚马森哥↑阿斯格昂↓"},{"Minute":"90","ClassType":"1","ScheduleType":"1","ScheduleID":"2399281","PlayerName":"David Datro Fofana(Assists:Wilson Odobert)","PlayerID":"205322","PlayerID2":"0","PlayerName_J":"科芬拿 (助攻:奥度伯特)"},{"Minute":"90","ClassType":"1","ScheduleType":"3","ScheduleID":"2399281","PlayerName":"David Datro Fofana","PlayerID":"205322","PlayerID2":"0","PlayerName_J":"科芬拿"},{"Minute":"90","ClassType":"0","ScheduleType":"4","ScheduleID":"2399281","PlayerName":null,"PlayerID":null,"PlayerID2":"0","PlayerName_J":null}],"scheduleEventList":{"event_info":[],"technic":{"14":{"leixing":"14","home_info":"44%","away_info":"56%"},"46":{"leixing":"46","home_info":"40%","away_info":"60%"},"43":{"leixing":"43","home_info":"111","away_info":"98"},"41":{"leixing":"41","home_info":"367","away_info":"473"},"42":{"leixing":"42","home_info":"76%","away_info":"77%"},"44":{"leixing":"44","home_info":"39","away_info":"48"},"45":{"leixing":"45","home_info":"2","away_info":"3"},"19":{"leixing":"19","home_info":"13","away_info":"9"},"15":{"leixing":"15","home_info":"48","away_info":"48"},"36":{"leixing":"36","home_info":"23","away_info":"25"},"38":{"leixing":"38","home_info":"13","away_info":"9"},"39":{"leixing":"39","home_info":"8","away_info":"0"},"40":{"leixing":"40","home_info":"23","away_info":"29"},"6":{"leixing":"6","home_info":"2","away_info":"13"},"20":{"leixing":"20","home_info":"6","away_info":"15"},"0":{"leixing":"0","home_info":"*","away_info":""},"3":{"leixing":"3","home_info":"12","away_info":"15"},"34":{"leixing":"34","home_info":"8","away_info":"8"},"37":{"leixing":"37","home_info":"4","away_info":"4"},"5":{"leixing":"5","home_info":"11","away_info":"7"},"4":{"leixing":"4","home_info":"4","away_info":"7"},"16":{"leixing":"16","home_info":"5","away_info":"2"},"8":{"leixing":"8","home_info":"7","away_info":"12"},"23":{"leixing":"23","home_info":"2","away_info":"2"},"9":{"leixing":"9","home_info":"1","away_info":"1"},"11":{"leixing":"11","home_info":"2","away_info":"2"}},"technicList":[{"leixing":"14","home_info":"44%","away_info":"56%"},{"leixing":"46","home_info":"40%","away_info":"60%"},{"leixing":"43","home_info":"111","away_info":"98"},{"leixing":"41","home_info":"367","away_info":"473"},{"leixing":"42","home_info":"76%","away_info":"77%"},{"leixing":"44","home_info":"39","away_info":"48"},{"leixing":"45","home_info":"2","away_info":"3"},{"leixing":"19","home_info":"13","away_info":"9"},{"leixing":"15","home_info":"48","away_info":"48"},{"leixing":"36","home_info":"23","away_info":"25"},{"leixing":"38","home_info":"13","away_info":"9"},{"leixing":"39","home_info":"8","away_info":"0"},{"leixing":"40","home_info":"23","away_info":"29"},{"leixing":"6","home_info":"2","away_info":"13"},{"leixing":"20","home_info":"6","away_info":"15"},{"leixing":"0","home_info":"*","away_info":""},{"leixing":"3","home_info":"12","away_info":"15"},{"leixing":"34","home_info":"8","away_info":"8"},{"leixing":"37","home_info":"4","away_info":"4"},{"leixing":"5","home_info":"11","away_info":"7"},{"leixing":"4","home_info":"4","away_info":"7"},{"leixing":"16","home_info":"5","away_info":"2"},{"leixing":"8","home_info":"7","away_info":"12"},{"leixing":"23","home_info":"2","away_info":"2"},{"leixing":"9","home_info":"1","away_info":"1"},{"leixing":"11","home_info":"2","away_info":"2"}]},"o_odds":{"o_home_first":"2.75","o_stand_first":"3.3","o_guest_first":"2.55","o_home":"2.9","o_stand":"3.3","o_guest":"2.4","o_home_r":"29","o_stand_r":"1.01","o_guest_r":"21","modifyTime":"2024-02-04 00:54:04","closePan":""},"y_odds":{"y_first_goal":"0.00","y_first_upOdds":"","y_first_downOdds":"","y_goal":"0.00","y_up":"1.90","y_down":"0.45","y_goal_r":"0.00","y_up_r":"1.08","y_down_r":"0.82","modifyTime":"2024-02-04 00:52:13","closePan":""},"total_score_odds":{"first_total_score_goal":"2.5","first_total_score_upOdds":"0.98","first_total_score_downOdds":"0.92","total_score_goal":"4.5","total_score_up":"10.5","total_score_down":"0.05","total_score_goal_r":"2.25","total_score_upOdds_r":"0.87","total_score_downOdds_r":"1.03","modifyTime":"2024-02-04 00:52:13","closePan":""}},{"lightning":"0","hasAnalysis":0,"isCollect":0,"id":"2399285","matchId":"2399285","league":"英格兰超级联赛","leagueShort":"英超","leagueColor":"#FF3333","home":"纽卡斯尔联","away":"卢顿","HomeTeamID":28,"GuestTeamID":372,"home_img":"https:\/\/images.footballant.com\/team\/28.png!webp","away_img":"https:\/\/images.footballant.com\/team\/372.png!webp","sclassID":"36","league_img":"https:\/\/images.footballant.com\/sclass\/36.png!webp","homeScore":4,"awayScore":4,"homeHalfScore":2,"awayHalfScore":2,"homered":0,"awayRed":0,"homeYellow":2,"awayYellow":2,"homeCorner":8,"guestCorner":2,"homeHalfCorner":3,"guestHalfCorner":2,"match_date":"02-03 23:00","match_time":"2024\/02\/03 23:00:00","match_time_timestamp":1706972400000,"state":"-1","explainList":"2;|;;;;","start_time":"2024\/02\/03 23:00:00","MatchTime2_timestamp":1706976397000,"start_time_timestamp":1706972400000,"event_list":[{"Minute":"7","ClassType":"1","ScheduleType":"1","ScheduleID":"2399285","PlayerName":"Sean Longstaff(Assists:Kieran Trippier)","PlayerID":"150848","PlayerID2":"0","PlayerName_J":"朗斯塔夫 (助攻:特里皮尔)"},{"Minute":"16","ClassType":"0","ScheduleType":"4","ScheduleID":"2399285","PlayerName":null,"PlayerID":null,"PlayerID2":"0","PlayerName_J":null},{"Minute":"21","ClassType":"0","ScheduleType":"1","ScheduleID":"2399285","PlayerName":"Gabriel Osho(Assists:Carlton Morris)","PlayerID":"170117","PlayerID2":"0","PlayerName_J":"加布里埃爾.奧紹 (助攻:莫里斯)"},{"Minute":"23","ClassType":"1","ScheduleType":"1","ScheduleID":"2399285","PlayerName":"Sean Longstaff","PlayerID":"150848","PlayerID2":"0","PlayerName_J":"朗斯塔夫"},{"Minute":"25","ClassType":"1","ScheduleType":"4","ScheduleID":"2399285","PlayerName":null,"PlayerID":null,"PlayerID2":"0","PlayerName_J":null},{"Minute":"26","ClassType":"1","ScheduleType":"4","ScheduleID":"2399285","PlayerName":null,"PlayerID":null,"PlayerID2":"0","PlayerName_J":null},{"Minute":"28","ClassType":"1","ScheduleType":"4","ScheduleID":"2399285","PlayerName":null,"PlayerID":null,"PlayerID2":"0","PlayerName_J":null},{"Minute":"39","ClassType":"0","ScheduleType":"4","ScheduleID":"2399285","PlayerName":null,"PlayerID":null,"PlayerID2":"0","PlayerName_J":null},{"Minute":"40","ClassType":"0","ScheduleType":"1","ScheduleID":"2399285","PlayerName":"Ross Barkley","PlayerID":"78733","PlayerID2":"0","PlayerName_J":"巴克利"},{"Minute":"45","ClassType":"1","ScheduleType":"4","ScheduleID":"2399285","PlayerName":null,"PlayerID":null,"PlayerID2":"0","PlayerName_J":null},{"Minute":"46","ClassType":"1","ScheduleType":"11","ScheduleID":"2399285","PlayerName":"Callum Wilson↑Anthony Gordon↓","PlayerID":"64744","PlayerID2":"0","PlayerName_J":"威尔逊↑戈登↓"},{"Minute":"56","ClassType":"1","ScheduleType":"3","ScheduleID":"2399285","PlayerName":"Dan Burn","PlayerID":"114892","PlayerID2":"0","PlayerName_J":"布恩"},{"Minute":"57","ClassType":"0","ScheduleType":"14","ScheduleID":"2399285","PlayerName":"Chiedozie Ogbene(Reason:Penalty awarded)","PlayerID":"149612","PlayerID2":"0","PlayerName_J":"奥贝纳 (原因:获得点球)"},{"Minute":"59","ClassType":"0","ScheduleType":"7","ScheduleID":"2399285","PlayerName":"Carlton Morris","PlayerID":"124066","PlayerID2":"0","PlayerName_J":"莫里斯"},{"Minute":"60","ClassType":"0","ScheduleType":"3","ScheduleID":"2399285","PlayerName":"Albert-Mboyo Sambi Lokonga","PlayerID":"161507","PlayerID2":"0","PlayerName_J":"罗孔加"},{"Minute":"62","ClassType":"0","ScheduleType":"1","ScheduleID":"2399285","PlayerName":"Elijah Anuoluwapo Adebayo(Assists:Ross Barkley)","PlayerID":"205096","PlayerID2":"0","PlayerName_J":"E.阿德巴約 (助攻:巴克利)"},{"Minute":"64","ClassType":"1","ScheduleType":"11","ScheduleID":"2399285","PlayerName":"Harvey Barnes↑Miguel Angel Almiron Rejala↓","PlayerID":"150254","PlayerID2":"0","PlayerName_J":"巴恩斯↑阿尔米隆↓"},{"Minute":"64","ClassType":"1","ScheduleType":"11","ScheduleID":"2399285","PlayerName":"Valentino Livramento↑Dan Burn↓","PlayerID":"210979","PlayerID2":"0","PlayerName_J":"V.利夫拉门托↑布恩↓"},{"Minute":"67","ClassType":"1","ScheduleType":"1","ScheduleID":"2399285","PlayerName":"Kieran Trippier(Assists:Bruno Guimaraes Rodriguez Moura)","PlayerID":"76653","PlayerID2":"0","PlayerName_J":"特里皮尔 (助攻:吉马良斯)"},{"Minute":"68","ClassType":"0","ScheduleType":"11","ScheduleID":"2399285","PlayerName":"Pelly Ruddock↑Jordan Clark↓","PlayerID":"116596","PlayerID2":"0","PlayerName_J":"鲁多克↑克拉克↓"},{"Minute":"72","ClassType":"1","ScheduleType":"4","ScheduleID":"2399285","PlayerName":null,"PlayerID":null,"PlayerID2":"0","PlayerName_J":null},{"Minute":"73","ClassType":"1","ScheduleType":"1","ScheduleID":"2399285","PlayerName":"Harvey Barnes(Assists:Lewis Miley)","PlayerID":"150254","PlayerID2":"0","PlayerName_J":"巴恩斯 (助攻:米利)"},{"Minute":"76","ClassType":"1","ScheduleType":"3","ScheduleID":"2399285","PlayerName":"Jacob Murphy","PlayerID":"119051","PlayerID2":"0","PlayerName_J":"墨菲"},{"Minute":"77","ClassType":"1","ScheduleType":"4","ScheduleID":"2399285","PlayerName":null,"PlayerID":null,"PlayerID2":"0","PlayerName_J":null},{"Minute":"79","ClassType":"0","ScheduleType":"11","ScheduleID":"2399285","PlayerName":"Jacob Brown↑Carlton Morris↓","PlayerID":"149482","PlayerID2":"0","PlayerName_J":"布朗↑莫里斯↓"},{"Minute":"79","ClassType":"0","ScheduleType":"11","ScheduleID":"2399285","PlayerName":"Reece Burke↑Alfie Doughty↓","PlayerID":"119064","PlayerID2":"0","PlayerName_J":"伯克↑道迪↓"},{"Minute":"82","ClassType":"1","ScheduleType":"4","ScheduleID":"2399285","PlayerName":null,"PlayerID":null,"PlayerID2":"0","PlayerName_J":null},{"Minute":"88","ClassType":"0","ScheduleType":"11","ScheduleID":"2399285","PlayerName":"Cauley Woodrow↑Elijah Anuoluwapo Adebayo↓","PlayerID":"116874","PlayerID2":"0","PlayerName_J":"伍德罗↑E.阿德巴約↓"},{"Minute":"90","ClassType":"0","ScheduleType":"3","ScheduleID":"2399285","PlayerName":"Gabriel Osho","PlayerID":"170117","PlayerID2":"0","PlayerName_J":"加布里埃爾.奧紹"},{"Minute":"90","ClassType":"1","ScheduleType":"4","ScheduleID":"2399285","PlayerName":null,"PlayerID":null,"PlayerID2":"0","PlayerName_J":null}],"scheduleEventList":{"event_info":[],"technic":{"14":{"leixing":"14","home_info":"54%","away_info":"46%"},"46":{"leixing":"46","home_info":"49%","away_info":"51%"},"41":{"leixing":"41","home_info":"403","away_info":"370"},"42":{"leixing":"42","home_info":"74%","away_info":"81%"},"20":{"leixing":"20","home_info":"4","away_info":"13"},"5":{"leixing":"5","home_info":"13","away_info":"15"},"40":{"leixing":"40","home_info":"24","away_info":"12"},"43":{"leixing":"43","home_info":"111","away_info":"95"},"44":{"leixing":"44","home_info":"57","away_info":"41"},"15":{"leixing":"15","home_info":"24","away_info":"24"},"36":{"leixing":"36","home_info":"9","away_info":"15"},"39":{"leixing":"39","home_info":"8","away_info":"14"},"8":{"leixing":"8","home_info":"13","away_info":"9"},"0":{"leixing":"0","home_info":"","away_info":"*"},"38":{"leixing":"38","home_info":"25","away_info":"13"},"3":{"leixing":"3","home_info":"19","away_info":"10"},"4":{"leixing":"4","home_info":"6","away_info":"8"},"34":{"leixing":"34","home_info":"13","away_info":"2"},"37":{"leixing":"37","home_info":"7","away_info":"2"},"19":{"leixing":"19","home_info":"25","away_info":"13"},"23":{"leixing":"23","home_info":"3","away_info":"2"},"45":{"leixing":"45","home_info":"4","away_info":"2"},"16":{"leixing":"16","home_info":"3","away_info":"2"},"6":{"leixing":"6","home_info":"8","away_info":"2"},"11":{"leixing":"11","home_info":"2","away_info":"2"}},"technicList":[{"leixing":"14","home_info":"54%","away_info":"46%"},{"leixing":"46","home_info":"49%","away_info":"51%"},{"leixing":"41","home_info":"403","away_info":"370"},{"leixing":"42","home_info":"74%","away_info":"81%"},{"leixing":"20","home_info":"4","away_info":"13"},{"leixing":"5","home_info":"13","away_info":"15"},{"leixing":"40","home_info":"24","away_info":"12"},{"leixing":"43","home_info":"111","away_info":"95"},{"leixing":"44","home_info":"57","away_info":"41"},{"leixing":"15","home_info":"24","away_info":"24"},{"leixing":"36","home_info":"9","away_info":"15"},{"leixing":"39","home_info":"8","away_info":"14"},{"leixing":"8","home_info":"13","away_info":"9"},{"leixing":"0","home_info":"","away_info":"*"},{"leixing":"38","home_info":"25","away_info":"13"},{"leixing":"3","home_info":"19","away_info":"10"},{"leixing":"4","home_info":"6","away_info":"8"},{"leixing":"34","home_info":"13","away_info":"2"},{"leixing":"37","home_info":"7","away_info":"2"},{"leixing":"19","home_info":"25","away_info":"13"},{"leixing":"23","home_info":"3","away_info":"2"},{"leixing":"45","home_info":"4","away_info":"2"},{"leixing":"16","home_info":"3","away_info":"2"},{"leixing":"6","home_info":"8","away_info":"2"},{"leixing":"11","home_info":"2","away_info":"2"}]},"o_odds":{"o_home_first":"1.36","o_stand_first":"5","o_guest_first":"8","o_home":"1.53","o_stand":"4.5","o_guest":"5.5","o_home_r":"15","o_stand_r":"1.05","o_guest_r":"23","modifyTime":"2024-02-04 01:00:00","closePan":""},"y_odds":{"y_first_goal":"-1.50","y_first_upOdds":"","y_first_downOdds":"","y_goal":"0.00","y_up":"0.42","y_down":"2.00","y_goal_r":"-1.00","y_up_r":"0.90","y_down_r":"1.00","modifyTime":"2024-02-04 00:58:28","closePan":""},"total_score_odds":{"first_total_score_goal":"3","first_total_score_upOdds":"0.88","first_total_score_downOdds":"1.02","total_score_goal":"8.5","total_score_up":"4","total_score_down":"0.17","total_score_goal_r":"3","total_score_upOdds_r":"1","total_score_downOdds_r":"0.9","modifyTime":"2024-02-04 00:58:28","closePan":""}},{"lightning":"0","hasAnalysis":0,"isCollect":0,"id":"2399283","matchId":"2399283","league":"英格兰超级联赛","leagueShort":"英超","leagueColor":"#FF3333","home":"埃弗顿","away":"托特纳姆热刺","HomeTeamID":31,"GuestTeamID":33,"home_img":"https:\/\/images.footballant.com\/team\/31.png!webp","away_img":"https:\/\/images.footballant.com\/team\/33.png!webp","sclassID":"36","league_img":"https:\/\/images.footballant.com\/sclass\/36.png!webp","homeScore":2,"awayScore":2,"homeHalfScore":1,"awayHalfScore":2,"homered":0,"awayRed":0,"homeYellow":3,"awayYellow":0,"homeCorner":9,"guestCorner":5,"homeHalfCorner":6,"guestHalfCorner":1,"match_date":"02-03 20:30","match_time":"2024\/02\/03 20:30:00","match_time_timestamp":1706963400000,"state":"-1","explainList":"1;|;;;;","start_time":"2024\/02\/03 20:30:00","MatchTime2_timestamp":1706967459000,"start_time_timestamp":1706963400000,"event_list":[{"Minute":"4","ClassType":"0","ScheduleType":"1","ScheduleID":"2399283","PlayerName":"Richarlison de Andrade(Assists:Iyenoma Destiny Udogie)","PlayerID":"138918","PlayerID2":"0","PlayerName_J":"理查利森 (助攻:乌多吉)"},{"Minute":"10","ClassType":"0","ScheduleType":"4","ScheduleID":"2399283","PlayerName":null,"PlayerID":null,"PlayerID2":"0","PlayerName_J":null},{"Minute":"12","ClassType":"1","ScheduleType":"4","ScheduleID":"2399283","PlayerName":null,"PlayerID":null,"PlayerID2":"0","PlayerName_J":null},{"Minute":"16","ClassType":"1","ScheduleType":"4","ScheduleID":"2399283","PlayerName":null,"PlayerID":null,"PlayerID2":"0","PlayerName_J":null},{"Minute":"25","ClassType":"1","ScheduleType":"4","ScheduleID":"2399283","PlayerName":null,"PlayerID":null,"PlayerID2":"0","PlayerName_J":null},{"Minute":"30","ClassType":"1","ScheduleType":"1","ScheduleID":"2399283","PlayerName":"Jack Harrison(Assists:James Tarkowski)","PlayerID":"140992","PlayerID2":"0","PlayerName_J":"哈里森 (助攻:塔科夫斯基)"},{"Minute":"30","ClassType":"1","ScheduleType":"4","ScheduleID":"2399283","PlayerName":null,"PlayerID":null,"PlayerID2":"0","PlayerName_J":null},{"Minute":"41","ClassType":"0","ScheduleType":"1","ScheduleID":"2399283","PlayerName":"Richarlison de Andrade(Assists:James Maddison)","PlayerID":"138918","PlayerID2":"0","PlayerName_J":"理查利森 (助攻:麦迪逊)"},{"Minute":"45","ClassType":"1","ScheduleType":"4","ScheduleID":"2399283","PlayerName":null,"PlayerID":null,"PlayerID2":"0","PlayerName_J":null},{"Minute":"45","ClassType":"1","ScheduleType":"4","ScheduleID":"2399283","PlayerName":null,"PlayerID":null,"PlayerID2":"0","PlayerName_J":null},{"Minute":"47","ClassType":"1","ScheduleType":"4","ScheduleID":"2399283","PlayerName":null,"PlayerID":null,"PlayerID2":"0","PlayerName_J":null},{"Minute":"51","ClassType":"0","ScheduleType":"4","ScheduleID":"2399283","PlayerName":null,"PlayerID":null,"PlayerID2":"0","PlayerName_J":null},{"Minute":"52","ClassType":"0","ScheduleType":"4","ScheduleID":"2399283","PlayerName":null,"PlayerID":null,"PlayerID2":"0","PlayerName_J":null},{"Minute":"54","ClassType":"1","ScheduleType":"4","ScheduleID":"2399283","PlayerName":null,"PlayerID":null,"PlayerID2":"0","PlayerName_J":null},{"Minute":"57","ClassType":"0","ScheduleType":"4","ScheduleID":"2399283","PlayerName":null,"PlayerID":null,"PlayerID2":"0","PlayerName_J":null},{"Minute":"60","ClassType":"1","ScheduleType":"3","ScheduleID":"2399283","PlayerName":"Ben Godfrey","PlayerID":"126331","PlayerID2":"0","PlayerName_J":"戈弗雷"},{"Minute":"64","ClassType":"0","ScheduleType":"11","ScheduleID":"2399283","PlayerName":"Dejan Kulusevski↑Brennan Johnson↓","PlayerID":"164751","PlayerID2":"0","PlayerName_J":"D·库卢塞夫斯基↑约翰逊↓"},{"Minute":"64","ClassType":"0","ScheduleType":"11","ScheduleID":"2399283","PlayerName":"Pape Matar Sarr↑Rodrigo Bentancur↓","PlayerID":"182375","PlayerID2":"0","PlayerName_J":"P.萨尔↑本坦库尔↓"},{"Minute":"67","ClassType":"0","ScheduleType":"4","ScheduleID":"2399283","PlayerName":null,"PlayerID":null,"PlayerID2":"0","PlayerName_J":null},{"Minute":"75","ClassType":"1","ScheduleType":"11","ScheduleID":"2399283","PlayerName":"Seamus Coleman↑Ben Godfrey↓","PlayerID":"63505","PlayerID2":"0","PlayerName_J":"科尔曼↑戈弗雷↓"},{"Minute":"80","ClassType":"1","ScheduleType":"11","ScheduleID":"2399283","PlayerName":"Youssef Chermiti↑Ashley Young↓","PlayerID":"220742","PlayerID2":"0","PlayerName_J":"尤斯夫卓亚米斯↑扬↓"},{"Minute":"84","ClassType":"1","ScheduleType":"4","ScheduleID":"2399283","PlayerName":null,"PlayerID":null,"PlayerID2":"0","PlayerName_J":null},{"Minute":"85","ClassType":"1","ScheduleType":"11","ScheduleID":"2399283","PlayerName":"Beto Betuncal↑Dominic Calvert-Lewin↓","PlayerID":"178187","PlayerID2":"0","PlayerName_J":"贝托↑勒温↓"},{"Minute":"85","ClassType":"1","ScheduleType":"11","ScheduleID":"2399283","PlayerName":"Lewis Dobbin↑Dwight Mcneil↓","PlayerID":"219312","PlayerID2":"0","PlayerName_J":"刘易斯·多宾↑麦克尼尔↓"},{"Minute":"86","ClassType":"0","ScheduleType":"11","ScheduleID":"2399283","PlayerName":"Oliver Skipp↑Timo Werner↓","PlayerID":"166729","PlayerID2":"0","PlayerName_J":"斯基普↑维尔纳↓"},{"Minute":"86","ClassType":"0","ScheduleType":"11","ScheduleID":"2399283","PlayerName":"Bryan Gil Salvatierra↑James Maddison↓","PlayerID":"171977","PlayerID2":"0","PlayerName_J":"吉尔↑麦迪逊↓"},{"Minute":"89","ClassType":"0","ScheduleType":"11","ScheduleID":"2399283","PlayerName":"Radu Dragusin↑Pierre Emile Hojbjerg↓","PlayerID":"201880","PlayerID2":"0","PlayerName_J":"R·德拉古辛↑霍伊别尔↓"},{"Minute":"90","ClassType":"1","ScheduleType":"3","ScheduleID":"2399283","PlayerName":"James Garner","PlayerID":"166736","PlayerID2":"0","PlayerName_J":"詹姆斯·加尔纳"},{"Minute":"90","ClassType":"1","ScheduleType":"1","ScheduleID":"2399283","PlayerName":"Jarrad Branthwaite","PlayerID":"182201","PlayerID2":"0","PlayerName_J":"贾拉德.布兰斯韦特"},{"Minute":"90","ClassType":"1","ScheduleType":"3","ScheduleID":"2399283","PlayerName":"Lewis Dobbin","PlayerID":"219312","PlayerID2":"0","PlayerName_J":"刘易斯·多宾"}],"scheduleEventList":{"event_info":[],"technic":{"14":{"leixing":"14","home_info":"44%","away_info":"56%"},"46":{"leixing":"46","home_info":"47%","away_info":"53%"},"43":{"leixing":"43","home_info":"123","away_info":"91"},"44":{"leixing":"44","home_info":"66","away_info":"39"},"0":{"leixing":"0","home_info":"*","away_info":""},"41":{"leixing":"41","home_info":"330","away_info":"457"},"36":{"leixing":"36","home_info":"20","away_info":"13"},"38":{"leixing":"38","home_info":"24","away_info":"22"},"20":{"leixing":"20","home_info":"16","away_info":"9"},"3":{"leixing":"3","home_info":"14","away_info":"9"},"4":{"leixing":"4","home_info":"5","away_info":"6"},"42":{"leixing":"42","home_info":"73%","away_info":"77%"},"15":{"leixing":"15","home_info":"48","away_info":"17"},"40":{"leixing":"40","home_info":"27","away_info":"30"},"19":{"leixing":"19","home_info":"24","away_info":"22"},"34":{"leixing":"34","home_info":"9","away_info":"3"},"23":{"leixing":"23","home_info":"1","away_info":"2"},"6":{"leixing":"6","home_info":"9","away_info":"5"},"45":{"leixing":"45","home_info":"6","away_info":"1"},"16":{"leixing":"16","home_info":"4","away_info":"3"},"5":{"leixing":"5","home_info":"6","away_info":"14"},"39":{"leixing":"39","home_info":"7","away_info":"8"},"37":{"leixing":"37","home_info":"3","away_info":"1"},"8":{"leixing":"8","home_info":"12","away_info":"10"},"9":{"leixing":"9","home_info":"5","away_info":"1"},"11":{"leixing":"11","home_info":"3","away_info":"0"}},"technicList":[{"leixing":"14","home_info":"44%","away_info":"56%"},{"leixing":"46","home_info":"47%","away_info":"53%"},{"leixing":"43","home_info":"123","away_info":"91"},{"leixing":"44","home_info":"66","away_info":"39"},{"leixing":"0","home_info":"*","away_info":""},{"leixing":"41","home_info":"330","away_info":"457"},{"leixing":"36","home_info":"20","away_info":"13"},{"leixing":"38","home_info":"24","away_info":"22"},{"leixing":"20","home_info":"16","away_info":"9"},{"leixing":"3","home_info":"14","away_info":"9"},{"leixing":"4","home_info":"5","away_info":"6"},{"leixing":"42","home_info":"73%","away_info":"77%"},{"leixing":"15","home_info":"48","away_info":"17"},{"leixing":"40","home_info":"27","away_info":"30"},{"leixing":"19","home_info":"24","away_info":"22"},{"leixing":"34","home_info":"9","away_info":"3"},{"leixing":"23","home_info":"1","away_info":"2"},{"leixing":"6","home_info":"9","away_info":"5"},{"leixing":"45","home_info":"6","away_info":"1"},{"leixing":"16","home_info":"4","away_info":"3"},{"leixing":"5","home_info":"6","away_info":"14"},{"leixing":"39","home_info":"7","away_info":"8"},{"leixing":"37","home_info":"3","away_info":"1"},{"leixing":"8","home_info":"12","away_info":"10"},{"leixing":"9","home_info":"5","away_info":"1"},{"leixing":"11","home_info":"3","away_info":"0"}]},"o_odds":{"o_home_first":"2.5","o_stand_first":"3.5","o_guest_first":"2.75","o_home":"3.1","o_stand":"3.75","o_guest":"2.15","o_home_r":"26","o_stand_r":"1.01","o_guest_r":"23","modifyTime":"2024-02-03 22:30:06","closePan":""},"y_odds":{"y_first_goal":"0.00","y_first_upOdds":"","y_first_downOdds":"","y_goal":"0.00","y_up":"1.12","y_down":"0.78","y_goal_r":"0.25","y_up_r":"0.93","y_down_r":"0.97","modifyTime":"2024-02-03 22:27:35","closePan":""},"total_score_odds":{"first_total_score_goal":"2.75","first_total_score_upOdds":"0.86","first_total_score_downOdds":"1.04","total_score_goal":"4.5","total_score_up":"7.5","total_score_down":"0.08","total_score_goal_r":"3","total_score_upOdds_r":"1.07","total_score_downOdds_r":"0.83","modifyTime":"2024-02-03 22:27:35","closePan":""}}]}}